<nfeProc xmlns="http://www.portalfiscal.inf.br/nfe" versao="4.00"><NFe xmlns="http://www.portalfiscal.inf.br/nfe"><infNFe Id="NFe13230708214295000372550010001809751550392342" versao="4.00"><ide><cUF>13</cUF><cNF>55039234</cNF><natOp>VENDA DE MERC. ADQUIRIDA OU RECEBIDA DE TERCEIROS</natOp><mod>55</mod><serie>1</serie><nNF>180975</nNF><dhEmi>2023-07-21T17:55:00-04:00</dhEmi><dhSaiEnt>2023-07-31T17:55:00-04:00</dhSaiEnt><tpNF>1</tpNF><idDest>1</idDest><cMunFG>1302603</cMunFG><tpImp>1</tpImp><tpEmis>1</tpEmis><cDV>2</cDV><tpAmb>1</tpAmb><finNFe>1</finNFe><indFinal>0</indFinal><indPres>9</indPres><indIntermed>1</indIntermed><procEmi>0</procEmi><verProc>1.3.229.015</verProc></ide><emit><CNPJ>08214295000372</CNPJ><xNome>SUPER CANCUN COMERCIO DE PRODUTOS ALIMENTICIOS LTDA</xNome><xFant>SERVE BEM BOMBONIERE FESTA E CIA</xFant><enderEmit><xLgr>RUA CERINA SOUTO</xLgr><nro>90</nro><xCpl>GALPAO01</xCpl><xBairro>PONTA NEGRA</xBairro><cMun>1302603</cMun><xMun>MANAUS</xMun><UF>AM</UF><CEP>69037208</CEP><cPais>1058</cPais><xPais>BRASIL</xPais><fone>9230261547</fone></enderEmit><IE>042297435</IE><CRT>3</CRT></emit><dest><CNPJ>07340876000126</CNPJ><xNome>HELILTON TEIXEIRA DE SOUZA</xNome><enderDest><xLgr>EST DO PENSADOR</xLgr><nro>857</nro><xBairro>SAO FRANCISCO</xBairro><cMun>1300409</cMun><xMun>BARCELOS</xMun><UF>AM</UF><CEP>69700000</CEP><cPais>1058</cPais><xPais>BRASIL</xPais><fone>97981878148</fone></enderDest><indIEDest>1</indIEDest><IE>042161096</IE></dest><entrega><CNPJ>07340876000126</CNPJ><xLgr>EST DO PENSADOR</xLgr><nro>857</nro><xBairro>SAO FRANCISCO</xBairro><cMun>1300409</cMun><xMun>BARCELOS</xMun><UF>AM</UF><CEP>69700000</CEP></entrega><det nItem="1"><prod><cProd>15013</cProd><cEAN>7896383073082</cEAN><xProd>AMENDOCHEF GRANULADO S/ SAL 12X1,05KG 12X1,05KG QTD. 1.00 CX</xProd><NCM>20081100</NCM><CEST>1703301</CEST><indEscala>S</indEscala><CFOP>5403</CFOP><uCom>PC</uCom><qCom>12.0000</qCom><vUnCom>27.5566666667</vUnCom><vProd>330.68</vProd><cEANTrib>7896383073082</cEANTrib><uTrib>PC</uTrib><qTrib>12.0000</qTrib><vUnTrib>27.5566666667</vUnTrib><indTot>1</indTot><xPed>645000391</xPed><nItemPed>2</nItemPed></prod><imposto><ICMS><ICMS60><orig>0</orig><CST>60</CST><vBCSTRet>212.42</vBCSTRet><pST>20.0000</pST><vICMSSubstituto>0.00</vICMSSubstituto><vICMSSTRet>31.82</vICMSSTRet></ICMS60></ICMS><IPI><cEnq>999</cEnq><IPITrib><CST>99</CST><vBC>0.00</vBC><pIPI>0.0000</pIPI><vIPI>0.00</vIPI></IPITrib></IPI><PIS><PISAliq><CST>01</CST><vBC>330.68</vBC><pPIS>0.6500</pPIS><vPIS>2.15</vPIS></PISAliq></PIS><COFINS><COFINSAliq><CST>01</CST><vBC>330.68</vBC><pCOFINS>3.0000</pCOFINS><vCOFINS>9.92</vCOFINS></COFINSAliq></COFINS></imposto></det><det nItem="2"><prod><cProd>12827</cProd><cEAN>7896058590500</cEAN><xProd>AMENDOIM JAPONES CARTELADO DORI 10X5X30G 10X5X30G QTD. 15.00 CX</xProd><NCM>20081100</NCM><CEST>1703300</CEST><indEscala>S</indEscala><CFOP>5403</CFOP><uCom>PC</uCom><qCom>150.0000</qCom><vUnCom>3.2754000000</vUnCom><vProd>491.31</vProd><cEANTrib>7896058590500</cEANTrib><uTrib>PC</uTrib><qTrib>150.0000</qTrib><vUnTrib>3.2754000000</vUnTrib><indTot>1</indTot><xPed>645000391</xPed><nItemPed>4</nItemPed></prod><imposto><ICMS><ICMS60><orig>0</orig><CST>60</CST><vBCSTRet>443.08</vBCSTRet><pST>20.0000</pST><vICMSSubstituto>0.00</vICMSSubstituto><vICMSSTRet>48.32</vICMSSTRet></ICMS60></ICMS><IPI><cEnq>999</cEnq><IPITrib><CST>99</CST><vBC>0.00</vBC><pIPI>0.0000</pIPI><vIPI>0.00</vIPI></IPITrib></IPI><PIS><PISAliq><CST>01</CST><vBC>491.31</vBC><pPIS>0.6500</pPIS><vPIS>3.19</vPIS></PISAliq></PIS><COFINS><COFINSAliq><CST>01</CST><vBC>491.31</vBC><pCOFINS>3.0000</pCOFINS><vCOFINS>14.74</vCOFINS></COFINSAliq></COFINS></imposto></det><det nItem="3"><prod><cProd>895</cProd><cEAN>7896058505023</cEAN><xProd>AMENDOIM JAPONES DORI 20X500G 20X500G QTD. 8.00 CX</xProd><NCM>20081100</NCM><CEST>1703300</CEST><indEscala>S</indEscala><CFOP>5403</CFOP><uCom>PC</uCom><qCom>160.0000</qCom><vUnCom>8.2296875000</vUnCom><vProd>1316.75</vProd><cEANTrib>7896058505023</cEANTrib><uTrib>PC</uTrib><qTrib>160.0000</qTrib><vUnTrib>8.2296875000</vUnTrib><indTot>1</indTot><xPed>645000391</xPed><nItemPed>5</nItemPed></prod><imposto><ICMS><ICMS60><orig>0</orig><CST>60</CST><vBCSTRet>1287.27</vBCSTRet><pST>20.0000</pST><vICMSSubstituto>0.00</vICMSSubstituto><vICMSSTRet>140.40</vICMSSTRet></ICMS60></ICMS><IPI><cEnq>999</cEnq><IPITrib><CST>99</CST><vBC>0.00</vBC><pIPI>0.0000</pIPI><vIPI>0.00</vIPI></IPITrib></IPI><PIS><PISAliq><CST>01</CST><vBC>1316.75</vBC><pPIS>0.6500</pPIS><vPIS>8.56</vPIS></PISAliq></PIS><COFINS><COFINSAliq><CST>01</CST><vBC>1316.75</vBC><pCOFINS>3.0000</pCOFINS><vCOFINS>39.50</vCOFINS></COFINSAliq></COFINS></imposto></det><det nItem="4"><prod><cProd>55755</cProd><cEAN>7896058599503</cEAN><xProd>AMENDOIM PETTIZ CEBOLA/SALSA CRO 24X350G 24X350G QTD. 1.00 CX</xProd><NCM>20081100</NCM><CFOP>5403</CFOP><uCom>PC</uCom><qCom>24.0000</qCom><vUnCom>10.2633333333</vUnCom><vProd>246.32</vProd><cEANTrib>7896058599503</cEANTrib><uTrib>PC</uTrib><qTrib>24.0000</qTrib><vUnTrib>10.2633333333</vUnTrib><indTot>1</indTot><xPed>645000391</xPed><nItemPed>6</nItemPed></prod><imposto><ICMS><ICMS60><orig>0</orig><CST>60</CST><vBCSTRet>193.46</vBCSTRet><pST>20.0000</pST><vICMSSubstituto>0.00</vICMSSubstituto><vICMSSTRet>21.10</vICMSSTRet></ICMS60></ICMS><IPI><cEnq>999</cEnq><IPITrib><CST>99</CST><vBC>0.00</vBC><pIPI>0.0000</pIPI><vIPI>0.00</vIPI></IPITrib></IPI><PIS><PISAliq><CST>01</CST><vBC>246.32</vBC><pPIS>0.6500</pPIS><vPIS>1.60</vPIS></PISAliq></PIS><COFINS><COFINSAliq><CST>01</CST><vBC>246.32</vBC><pCOFINS>3.0000</pCOFINS><vCOFINS>7.39</vCOFINS></COFINSAliq></COFINS></imposto></det><det nItem="5"><prod><cProd>1230</cProd><cEAN>7896058503791</cEAN><xProd>AMENDOIM PETTIZ CROC CEBOLA SALSA 16X500 16X500G QTD. 1.00 CX</xProd><NCM>20081100</NCM><CEST>1703300</CEST><indEscala>S</indEscala><CFOP>5403</CFOP><uCom>PC</uCom><qCom>16.0000</qCom><vUnCom>12.6537500000</vUnCom><vProd>202.46</vProd><cEANTrib>7896058503791</cEANTrib><uTrib>PC</uTrib><qTrib>16.0000</qTrib><vUnTrib>12.6537500000</vUnTrib><indTot>1</indTot><xPed>645000391</xPed><nItemPed>7</nItemPed></prod><imposto><ICMS><ICMS60><orig>0</orig><CST>60</CST><vBCSTRet>159.36</vBCSTRet><pST>20.0000</pST><vICMSSubstituto>0.00</vICMSSubstituto><vICMSSTRet>17.38</vICMSSTRet></ICMS60></ICMS><IPI><cEnq>999</cEnq><IPITrib><CST>99</CST><vBC>0.00</vBC><pIPI>0.0000</pIPI><vIPI>0.00</vIPI></IPITrib></IPI><PIS><PISAliq><CST>01</CST><vBC>202.46</vBC><pPIS>0.6500</pPIS><vPIS>1.32</vPIS></PISAliq></PIS><COFINS><COFINSAliq><CST>01</CST><vBC>202.46</vBC><pCOFINS>3.0000</pCOFINS><vCOFINS>6.07</vCOFINS></COFINSAliq></COFINS></imposto></det><det nItem="6"><prod><cProd>1229</cProd><cEAN>7896058503760</cEAN><xProd>AMENDOIM PETTIZ CROC NATURAL DORI 16X500 16X500G QTD. 1.00 CX</xProd><NCM>20081100</NCM><CEST>1703300</CEST><indEscala>S</indEscala><CFOP>5403</CFOP><uCom>PC</uCom><qCom>16.0000</qCom><vUnCom>12.6537500000</vUnCom><vProd>202.46</vProd><cEANTrib>7896058503760</cEANTrib><uTrib>PC</uTrib><qTrib>16.0000</qTrib><vUnTrib>12.6537500000</vUnTrib><indTot>1</indTot><xPed>645000391</xPed><nItemPed>8</nItemPed></prod><imposto><ICMS><ICMS60><orig>0</orig><CST>60</CST><vBCSTRet>159.36</vBCSTRet><pST>20.0000</pST><vICMSSubstituto>0.00</vICMSSubstituto><vICMSSTRet>17.38</vICMSSTRet></ICMS60></ICMS><IPI><cEnq>999</cEnq><IPITrib><CST>99</CST><vBC>0.00</vBC><pIPI>0.0000</pIPI><vIPI>0.00</vIPI></IPITrib></IPI><PIS><PISAliq><CST>01</CST><vBC>202.46</vBC><pPIS>0.6500</pPIS><vPIS>1.32</vPIS></PISAliq></PIS><COFINS><COFINSAliq><CST>01</CST><vBC>202.46</vBC><pCOFINS>3.0000</pCOFINS><vCOFINS>6.07</vCOFINS></COFINSAliq></COFINS></imposto></det><det nItem="7"><prod><cProd>1231</cProd><cEAN>7896058503845</cEAN><xProd>AMENDOIM PETTIZ CROC PIMENTA VERM 16X500 16X500G QTD. 1.00 CX</xProd><NCM>20081100</NCM><CEST>1703300</CEST><indEscala>S</indEscala><CFOP>5403</CFOP><uCom>PC</uCom><qCom>16.0000</qCom><vUnCom>12.6537500000</vUnCom><vProd>202.46</vProd><cEANTrib>7896058503845</cEANTrib><uTrib>PC</uTrib><qTrib>16.0000</qTrib><vUnTrib>12.6537500000</vUnTrib><indTot>1</indTot><xPed>645000391</xPed><nItemPed>9</nItemPed></prod><imposto><ICMS><ICMS60><orig>0</orig><CST>60</CST><vBCSTRet>159.36</vBCSTRet><pST>20.0000</pST><vICMSSubstituto>0.00</vICMSSubstituto><vICMSSTRet>17.38</vICMSSTRet></ICMS60></ICMS><IPI><cEnq>999</cEnq><IPITrib><CST>99</CST><vBC>0.00</vBC><pIPI>0.0000</pIPI><vIPI>0.00</vIPI></IPITrib></IPI><PIS><PISAliq><CST>01</CST><vBC>202.46</vBC><pPIS>0.6500</pPIS><vPIS>1.32</vPIS></PISAliq></PIS><COFINS><COFINSAliq><CST>01</CST><vBC>202.46</vBC><pCOFINS>3.0000</pCOFINS><vCOFINS>6.07</vCOFINS></COFINSAliq></COFINS></imposto></det><det nItem="8"><prod><cProd>13592</cProd><cEAN>7896058507690</cEAN><xProd>AMENDOIM PETTIZ NATURAL CROC 12X1,010KG 12X1,010KG QTD. 1.00 CX</xProd><NCM>20081100</NCM><CEST>1703301</CEST><indEscala>S</indEscala><CFOP>5403</CFOP><uCom>PC</uCom><qCom>12.0000</qCom><vUnCom>24.2758333333</vUnCom><vProd>291.31</vProd><cEANTrib>7896058507690</cEANTrib><uTrib>PC</uTrib><qTrib>12.0000</qTrib><vUnTrib>24.2758333333</vUnTrib><indTot>1</indTot><xPed>645000391</xPed><nItemPed>10</nItemPed></prod><imposto><ICMS><ICMS60><orig>0</orig><CST>60</CST><vBCSTRet>228.77</vBCSTRet><pST>20.0000</pST><vICMSSubstituto>0.00</vICMSSubstituto><vICMSSTRet>24.95</vICMSSTRet></ICMS60></ICMS><IPI><cEnq>999</cEnq><IPITrib><CST>99</CST><vBC>0.00</vBC><pIPI>0.0000</pIPI><vIPI>0.00</vIPI></IPITrib></IPI><PIS><PISAliq><CST>01</CST><vBC>291.31</vBC><pPIS>0.6500</pPIS><vPIS>1.89</vPIS></PISAliq></PIS><COFINS><COFINSAliq><CST>01</CST><vBC>291.31</vBC><pCOFINS>3.0000</pCOFINS><vCOFINS>8.74</vCOFINS></COFINSAliq></COFINS></imposto></det><det nItem="9"><prod><cProd>55756</cProd><cEAN>7896058599510</cEAN><xProd>AMENDOIM PETTIZ NATURAL CROCANTE 24X350G 24X350G QTD. 1.00 CX</xProd><NCM>20081100</NCM><CFOP>5403</CFOP><uCom>PC</uCom><qCom>24.0000</qCom><vUnCom>10.2633333333</vUnCom><vProd>246.32</vProd><cEANTrib>7896058599510</cEANTrib><uTrib>PC</uTrib><qTrib>24.0000</qTrib><vUnTrib>10.2633333333</vUnTrib><indTot>1</indTot><xPed>645000391</xPed><nItemPed>11</nItemPed></prod><imposto><ICMS><ICMS60><orig>0</orig><CST>60</CST><vBCSTRet>193.46</vBCSTRet><pST>20.0000</pST><vICMSSubstituto>0.00</vICMSSubstituto><vICMSSTRet>21.10</vICMSSTRet></ICMS60></ICMS><IPI><cEnq>999</cEnq><IPITrib><CST>99</CST><vBC>0.00</vBC><pIPI>0.0000</pIPI><vIPI>0.00</vIPI></IPITrib></IPI><PIS><PISAliq><CST>01</CST><vBC>246.32</vBC><pPIS>0.6500</pPIS><vPIS>1.60</vPIS></PISAliq></PIS><COFINS><COFINSAliq><CST>01</CST><vBC>246.32</vBC><pCOFINS>3.0000</pCOFINS><vCOFINS>7.39</vCOFINS></COFINSAliq></COFINS></imposto></det><det nItem="10"><prod><cProd>51775</cProd><cEAN>7896202892108</cEAN><xProd>BALA DE BANANA OLIVEIRA 100X50G 100X50G QTD. 1.00 CX</xProd><NCM>17049020</NCM><CEST>2804100</CEST><indEscala>S</indEscala><CFOP>5102</CFOP><uCom>PC</uCom><qCom>100.0000</qCom><vUnCom>1.9215000000</vUnCom><vProd>192.15</vProd><cEANTrib>7896202892108</cEANTrib><uTrib>PC</uTrib><qTrib>100.0000</qTrib><vUnTrib>1.9215000000</vUnTrib><indTot>1</indTot><xPed>645000391</xPed><nItemPed>12</nItemPed></prod><imposto><vTotTrib>38.43</vTotTrib><ICMS><ICMS00><orig>0</orig><CST>00</CST><modBC>3</modBC><vBC>192.15</vBC><pICMS>20.0000</pICMS><vICMS>38.43</vICMS></ICMS00></ICMS><IPI><cEnq>999</cEnq><IPITrib><CST>99</CST><vBC>0.00</vBC><pIPI>0.0000</pIPI><vIPI>0.00</vIPI></IPITrib></IPI><PIS><PISAliq><CST>01</CST><vBC>192.15</vBC><pPIS>0.6500</pPIS><vPIS>1.25</vPIS></PISAliq></PIS><COFINS><COFINSAliq><CST>01</CST><vBC>192.15</vBC><pCOFINS>3.0000</pCOFINS><vCOFINS>5.76</vCOFINS></COFINSAliq></COFINS></imposto></det><det nItem="11"><prod><cProd>1110</cProd><cEAN>7896321000378</cEAN><xProd>BALA FRUTA RECHEADA FLORESTAL 20X1KG 20X1KG QTD. 1.00 FD</xProd><NCM>17049020</NCM><CEST>2804100</CEST><indEscala>S</indEscala><CFOP>5102</CFOP><uCom>PC</uCom><qCom>20.0000</qCom><vUnCom>16.2155000000</vUnCom><vProd>324.31</vProd><cEANTrib>7896321000378</cEANTrib><uTrib>PC</uTrib><qTrib>20.0000</qTrib><vUnTrib>16.2155000000</vUnTrib><indTot>1</indTot><xPed>645000391</xPed><nItemPed>13</nItemPed></prod><imposto><vTotTrib>64.86</vTotTrib><ICMS><ICMS00><orig>0</orig><CST>00</CST><modBC>3</modBC><vBC>324.31</vBC><pICMS>20.0000</pICMS><vICMS>64.86</vICMS></ICMS00></ICMS><IPI><cEnq>999</cEnq><IPITrib><CST>99</CST><vBC>0.00</vBC><pIPI>0.0000</pIPI><vIPI>0.00</vIPI></IPITrib></IPI><PIS><PISAliq><CST>01</CST><vBC>324.31</vBC><pPIS>0.6500</pPIS><vPIS>2.11</vPIS></PISAliq></PIS><COFINS><COFINSAliq><CST>01</CST><vBC>324.31</vBC><pCOFINS>3.0000</pCOFINS><vCOFINS>9.73</vCOFINS></COFINSAliq></COFINS></imposto></det><det nItem="12"><prod><cProd>1103</cProd><cEAN>7896321000057</cEAN><xProd>BALA FRUTA RECHEADA FLORESTAL 22X500G 22X500G QTD. 1.00 FD</xProd><NCM>17049020</NCM><CEST>2804100</CEST><indEscala>S</indEscala><CFOP>5102</CFOP><uCom>PC</uCom><qCom>22.0000</qCom><vUnCom>8.3886363636</vUnCom><vProd>184.55</vProd><cEANTrib>7896321000057</cEANTrib><uTrib>PC</uTrib><qTrib>22.0000</qTrib><vUnTrib>8.3886363636</vUnTrib><indTot>1</indTot><xPed>645000391</xPed><nItemPed>14</nItemPed></prod><imposto><vTotTrib>36.91</vTotTrib><ICMS><ICMS00><orig>0</orig><CST>00</CST><modBC>3</modBC><vBC>184.55</vBC><pICMS>20.0000</pICMS><vICMS>36.91</vICMS></ICMS00></ICMS><IPI><cEnq>999</cEnq><IPITrib><CST>99</CST><vBC>0.00</vBC><pIPI>0.0000</pIPI><vIPI>0.00</vIPI></IPITrib></IPI><PIS><PISAliq><CST>01</CST><vBC>184.55</vBC><pPIS>0.6500</pPIS><vPIS>1.20</vPIS></PISAliq></PIS><COFINS><COFINSAliq><CST>01</CST><vBC>184.55</vBC><pCOFINS>3.0000</pCOFINS><vCOFINS>5.54</vCOFINS></COFINSAliq></COFINS></imposto></det><det nItem="13"><prod><cProd>1112</cProd><cEAN>7896321000149</cEAN><xProd>BALA MENTA FLORESTAL 20X1KG 20X1KG QTD. 1.00 FD</xProd><NCM>17049020</NCM><CEST>2804100</CEST><indEscala>S</indEscala><CFOP>5102</CFOP><uCom>PC</uCom><qCom>20.0000</qCom><vUnCom>16.2155000000</vUnCom><vProd>324.31</vProd><cEANTrib>7896321000149</cEANTrib><uTrib>PC</uTrib><qTrib>20.0000</qTrib><vUnTrib>16.2155000000</vUnTrib><indTot>1</indTot><xPed>645000391</xPed><nItemPed>15</nItemPed></prod><imposto><vTotTrib>64.86</vTotTrib><ICMS><ICMS00><orig>0</orig><CST>00</CST><modBC>3</modBC><vBC>324.31</vBC><pICMS>20.0000</pICMS><vICMS>64.86</vICMS></ICMS00></ICMS><IPI><cEnq>999</cEnq><IPITrib><CST>99</CST><vBC>0.00</vBC><pIPI>0.0000</pIPI><vIPI>0.00</vIPI></IPITrib></IPI><PIS><PISAliq><CST>01</CST><vBC>324.31</vBC><pPIS>0.6500</pPIS><vPIS>2.11</vPIS></PISAliq></PIS><COFINS><COFINSAliq><CST>01</CST><vBC>324.31</vBC><pCOFINS>3.0000</pCOFINS><vCOFINS>9.73</vCOFINS></COFINSAliq></COFINS></imposto></det><det nItem="14"><prod><cProd>55551</cProd><cEAN>7896321028006</cEAN><xProd>BALA RECHEADA MORANGUINHO 22X500G 22X500G QTD. 1.00 CX</xProd><NCM>17049020</NCM><CEST>2804100</CEST><indEscala>S</indEscala><CFOP>5102</CFOP><uCom>PC</uCom><qCom>22.0000</qCom><vUnCom>8.4359090909</vUnCom><vProd>185.59</vProd><cEANTrib>7896321028006</cEANTrib><uTrib>PC</uTrib><qTrib>22.0000</qTrib><vUnTrib>8.4359090909</vUnTrib><indTot>1</indTot><xPed>645000391</xPed><nItemPed>16</nItemPed></prod><imposto><vTotTrib>37.12</vTotTrib><ICMS><ICMS00><orig>0</orig><CST>00</CST><modBC>3</modBC><vBC>185.59</vBC><pICMS>20.0000</pICMS><vICMS>37.12</vICMS></ICMS00></ICMS><IPI><cEnq>999</cEnq><IPITrib><CST>99</CST><vBC>0.00</vBC><pIPI>0.0000</pIPI><vIPI>0.00</vIPI></IPITrib></IPI><PIS><PISAliq><CST>01</CST><vBC>185.59</vBC><pPIS>0.6500</pPIS><vPIS>1.21</vPIS></PISAliq></PIS><COFINS><COFINSAliq><CST>01</CST><vBC>185.59</vBC><pCOFINS>3.0000</pCOFINS><vCOFINS>5.57</vCOFINS></COFINSAliq></COFINS></imposto></det><det nItem="15"><prod><cProd>563</cProd><cEAN>7896061300189</cEAN><xProd>BISC TUCS QUEIJO 100G 30X100G QTD. 5.00 CX</xProd><NCM>19053100</NCM><CEST>1705300</CEST><indEscala>S</indEscala><CFOP>5403</CFOP><uCom>PC</uCom><qCom>150.0000</qCom><vUnCom>1.8231333333</vUnCom><vProd>273.47</vProd><cEANTrib>7896061300189</cEANTrib><uTrib>PC</uTrib><qTrib>150.0000</qTrib><vUnTrib>1.8231333333</vUnTrib><indTot>1</indTot><xPed>645000391</xPed><nItemPed>17</nItemPed></prod><imposto><ICMS><ICMS60><orig>0</orig><CST>60</CST><vBCSTRet>192.66</vBCSTRet><pST>20.0000</pST><vICMSSubstituto>0.00</vICMSSubstituto><vICMSSTRet>27.30</vICMSSTRet></ICMS60></ICMS><IPI><cEnq>999</cEnq><IPITrib><CST>99</CST><vBC>0.00</vBC><pIPI>0.0000</pIPI><vIPI>0.00</vIPI></IPITrib></IPI><PIS><PISAliq><CST>01</CST><vBC>273.46</vBC><pPIS>0.6500</pPIS><vPIS>1.78</vPIS></PISAliq></PIS><COFINS><COFINSAliq><CST>01</CST><vBC>273.46</vBC><pCOFINS>3.0000</pCOFINS><vCOFINS>8.20</vCOFINS></COFINSAliq></COFINS></imposto></det><det nItem="16"><prod><cProd>548</cProd><cEAN>7896061300677</cEAN><xProd>BISC TUCS TRADICIONAL 100G 30X100G QTD. 5.00 CX</xProd><NCM>19053100</NCM><CFOP>5403</CFOP><uCom>PC</uCom><qCom>150.0000</qCom><vUnCom>1.8231333333</vUnCom><vProd>273.47</vProd><cEANTrib>7896061300677</cEANTrib><uTrib>PC</uTrib><qTrib>150.0000</qTrib><vUnTrib>1.8231333333</vUnTrib><indTot>1</indTot><xPed>645000391</xPed><nItemPed>18</nItemPed></prod><imposto><ICMS><ICMS60><orig>0</orig><CST>60</CST><vBCSTRet>192.66</vBCSTRet><pST>20.0000</pST><vICMSSubstituto>0.00</vICMSSubstituto><vICMSSTRet>27.30</vICMSSTRet></ICMS60></ICMS><IPI><cEnq>999</cEnq><IPITrib><CST>99</CST><vBC>0.00</vBC><pIPI>0.0000</pIPI><vIPI>0.00</vIPI></IPITrib></IPI><PIS><PISAliq><CST>01</CST><vBC>273.46</vBC><pPIS>0.6500</pPIS><vPIS>1.78</vPIS></PISAliq></PIS><COFINS><COFINSAliq><CST>01</CST><vBC>273.46</vBC><pCOFINS>3.0000</pCOFINS><vCOFINS>8.20</vCOFINS></COFINSAliq></COFINS></imposto></det><det nItem="17"><prod><cProd>12993</cProd><cEAN>7896408440806</cEAN><xProd>BISCOITO RECH CHOCOLATE MYBIT 30X110G 30X110G QTD. 10.00 CX</xProd><NCM>19053100</NCM><CFOP>5403</CFOP><uCom>PC</uCom><qCom>300.0000</qCom><vUnCom>1.5965000000</vUnCom><vProd>478.95</vProd><cEANTrib>7896408440806</cEANTrib><uTrib>PC</uTrib><qTrib>300.0000</qTrib><vUnTrib>1.5965000000</vUnTrib><indTot>1</indTot><xPed>645000391</xPed><nItemPed>19</nItemPed></prod><imposto><ICMS><ICMS60><orig>0</orig><CST>60</CST><vBCSTRet>322.27</vBCSTRet><pST>20.0000</pST><vICMSSubstituto>0.00</vICMSSubstituto><vICMSSTRet>46.34</vICMSSTRet></ICMS60></ICMS><IPI><cEnq>999</cEnq><IPITrib><CST>99</CST><vBC>0.00</vBC><pIPI>0.0000</pIPI><vIPI>0.00</vIPI></IPITrib></IPI><PIS><PISAliq><CST>01</CST><vBC>478.95</vBC><pPIS>0.6500</pPIS><vPIS>3.11</vPIS></PISAliq></PIS><COFINS><COFINSAliq><CST>01</CST><vBC>478.95</vBC><pCOFINS>3.0000</pCOFINS><vCOFINS>14.37</vCOFINS></COFINSAliq></COFINS></imposto></det><det nItem="18"><prod><cProd>12994</cProd><cEAN>7896408440820</cEAN><xProd>BISCOITO RECH MORANGO MYBIT 30X110G 30X110G QTD. 10.00 CX</xProd><NCM>19053100</NCM><CEST>1705400</CEST><indEscala>S</indEscala><CFOP>5403</CFOP><uCom>PC</uCom><qCom>300.0000</qCom><vUnCom>1.5965000000</vUnCom><vProd>478.95</vProd><cEANTrib>7896408440820</cEANTrib><uTrib>PC</uTrib><qTrib>300.0000</qTrib><vUnTrib>1.5965000000</vUnTrib><indTot>1</indTot><xPed>645000391</xPed><nItemPed>20</nItemPed></prod><imposto><ICMS><ICMS60><orig>0</orig><CST>60</CST><vBCSTRet>322.27</vBCSTRet><pST>20.0000</pST><vICMSSubstituto>0.00</vICMSSubstituto><vICMSSTRet>46.34</vICMSSTRet></ICMS60></ICMS><IPI><cEnq>999</cEnq><IPITrib><CST>99</CST><vBC>0.00</vBC><pIPI>0.0000</pIPI><vIPI>0.00</vIPI></IPITrib></IPI><PIS><PISAliq><CST>01</CST><vBC>478.95</vBC><pPIS>0.6500</pPIS><vPIS>3.11</vPIS></PISAliq></PIS><COFINS><COFINSAliq><CST>01</CST><vBC>478.95</vBC><pCOFINS>3.0000</pCOFINS><vCOFINS>14.37</vCOFINS></COFINSAliq></COFINS></imposto></det><det nItem="19"><prod><cProd>53510</cProd><cEAN>7897652605805</cEAN><xProd>CARAMELO KIDLAND LEITE 500G 500G QTD. 10.00 PC</xProd><NCM>17049020</NCM><CEST>2804100</CEST><indEscala>S</indEscala><CFOP>5102</CFOP><uCom>PC</uCom><qCom>10.0000</qCom><vUnCom>9.7430000000</vUnCom><vProd>97.43</vProd><cEANTrib>7897652605805</cEANTrib><uTrib>PC</uTrib><qTrib>10.0000</qTrib><vUnTrib>9.7430000000</vUnTrib><indTot>1</indTot><xPed>645000391</xPed><nItemPed>21</nItemPed></prod><imposto><vTotTrib>19.49</vTotTrib><ICMS><ICMS00><orig>0</orig><CST>00</CST><modBC>3</modBC><vBC>97.43</vBC><pICMS>20.0000</pICMS><vICMS>19.49</vICMS></ICMS00></ICMS><IPI><cEnq>999</cEnq><IPITrib><CST>99</CST><vBC>0.00</vBC><pIPI>0.0000</pIPI><vIPI>0.00</vIPI></IPITrib></IPI><PIS><PISAliq><CST>01</CST><vBC>97.43</vBC><pPIS>0.6500</pPIS><vPIS>0.63</vPIS></PISAliq></PIS><COFINS><COFINSAliq><CST>01</CST><vBC>97.43</vBC><pCOFINS>3.0000</pCOFINS><vCOFINS>2.92</vCOFINS></COFINSAliq></COFINS></imposto><infAdProd>PERC.PARC.FCI: 0 - N. FCI: BD4A20C3-8503-4205-95B6-671E96C0CA27</infAdProd></det><det nItem="20"><prod><cProd>13722</cProd><cEAN>7898279794842</cEAN><xProd>CHICLE FINI MELANCIA 12X80G 12X80G QTD. 1.00 CX</xProd><NCM>17041000</NCM><CEST>2804100</CEST><indEscala>S</indEscala><CFOP>5102</CFOP><uCom>PC</uCom><qCom>12.0000</qCom><vUnCom>7.3108333333</vUnCom><vProd>87.73</vProd><cEANTrib>7898279794842</cEANTrib><uTrib>PC</uTrib><qTrib>12.0000</qTrib><vUnTrib>7.3108333333</vUnTrib><indTot>1</indTot><xPed>645000391</xPed><nItemPed>22</nItemPed></prod><imposto><vTotTrib>17.55</vTotTrib><ICMS><ICMS00><orig>0</orig><CST>00</CST><modBC>3</modBC><vBC>87.73</vBC><pICMS>20.0000</pICMS><vICMS>17.55</vICMS></ICMS00></ICMS><IPI><cEnq>999</cEnq><IPITrib><CST>99</CST><vBC>0.00</vBC><pIPI>0.0000</pIPI><vIPI>0.00</vIPI></IPITrib></IPI><PIS><PISAliq><CST>01</CST><vBC>87.73</vBC><pPIS>0.6500</pPIS><vPIS>0.57</vPIS></PISAliq></PIS><COFINS><COFINSAliq><CST>01</CST><vBC>87.73</vBC><pCOFINS>3.0000</pCOFINS><vCOFINS>2.63</vCOFINS></COFINSAliq></COFINS></imposto></det><det nItem="21"><prod><cProd>13623</cProd><cEAN>7898279795061</cEAN><xProd>CHICLE FINI SALADA DE FRUTAS 12X80G 12X80G QTD. 1.00 CX</xProd><NCM>17041000</NCM><CEST>2804100</CEST><indEscala>S</indEscala><CFOP>5102</CFOP><uCom>PC</uCom><qCom>12.0000</qCom><vUnCom>7.3108333333</vUnCom><vProd>87.73</vProd><cEANTrib>7898279795061</cEANTrib><uTrib>PC</uTrib><qTrib>12.0000</qTrib><vUnTrib>7.3108333333</vUnTrib><indTot>1</indTot><xPed>645000391</xPed><nItemPed>23</nItemPed></prod><imposto><vTotTrib>17.55</vTotTrib><ICMS><ICMS00><orig>0</orig><CST>00</CST><modBC>3</modBC><vBC>87.73</vBC><pICMS>20.0000</pICMS><vICMS>17.55</vICMS></ICMS00></ICMS><IPI><cEnq>999</cEnq><IPITrib><CST>99</CST><vBC>0.00</vBC><pIPI>0.0000</pIPI><vIPI>0.00</vIPI></IPITrib></IPI><PIS><PISAliq><CST>01</CST><vBC>87.73</vBC><pPIS>0.6500</pPIS><vPIS>0.57</vPIS></PISAliq></PIS><COFINS><COFINSAliq><CST>01</CST><vBC>87.73</vBC><pCOFINS>3.0000</pCOFINS><vCOFINS>2.63</vCOFINS></COFINSAliq></COFINS></imposto></det><det nItem="22"><prod><cProd>58859</cProd><cEAN>7898094764389</cEAN><xProd>CHOC OVINHOS DE OURO POTE 12X475G 12X475G QTD. 1.00 CX</xProd><NCM>18063220</NCM><CFOP>5403</CFOP><uCom>PT</uCom><qCom>12.0000</qCom><vUnCom>13.6850000000</vUnCom><vProd>164.22</vProd><cEANTrib>7898094764389</cEANTrib><uTrib>PT</uTrib><qTrib>12.0000</qTrib><vUnTrib>13.6850000000</vUnTrib><indTot>1</indTot><xPed>645000391</xPed><nItemPed>24</nItemPed></prod><imposto><ICMS><ICMS60><orig>0</orig><CST>60</CST><vBCSTRet>107.39</vBCSTRet><pST>20.0000</pST><vICMSSubstituto>0.00</vICMSSubstituto><vICMSSTRet>15.70</vICMSSTRet></ICMS60></ICMS><IPI><cEnq>999</cEnq><IPITrib><CST>99</CST><vBC>0.00</vBC><pIPI>0.0000</pIPI><vIPI>0.00</vIPI></IPITrib></IPI><PIS><PISAliq><CST>01</CST><vBC>164.22</vBC><pPIS>0.6500</pPIS><vPIS>1.07</vPIS></PISAliq></PIS><COFINS><COFINSAliq><CST>01</CST><vBC>164.22</vBC><pCOFINS>3.0000</pCOFINS><vCOFINS>4.93</vCOFINS></COFINSAliq></COFINS></imposto></det><det nItem="23"><prod><cProd>3425</cProd><cEAN>7896383000415</cEAN><xProd>COLORETI TRADICIONAL 12X500G 12X500G QTD. 1.00 CX</xProd><NCM>18069000</NCM><CEST>1700900</CEST><indEscala>S</indEscala><CFOP>5403</CFOP><uCom>UN</uCom><qCom>12.0000</qCom><vUnCom>15.8875000000</vUnCom><vProd>190.65</vProd><cEANTrib>7896383000415</cEANTrib><uTrib>UN</uTrib><qTrib>12.0000</qTrib><vUnTrib>15.8875000000</vUnTrib><indTot>1</indTot><xPed>645000391</xPed><nItemPed>25</nItemPed></prod><imposto><ICMS><ICMS60><orig>0</orig><CST>60</CST><vBCSTRet>117.77</vBCSTRet><pST>20.0000</pST><vICMSSubstituto>0.00</vICMSSubstituto><vICMSSTRet>17.22</vICMSSTRet></ICMS60></ICMS><IPI><cEnq>999</cEnq><IPITrib><CST>99</CST><vBC>0.00</vBC><pIPI>0.0000</pIPI><vIPI>0.00</vIPI></IPITrib></IPI><PIS><PISAliq><CST>01</CST><vBC>190.65</vBC><pPIS>0.6500</pPIS><vPIS>1.24</vPIS></PISAliq></PIS><COFINS><COFINSAliq><CST>01</CST><vBC>190.65</vBC><pCOFINS>3.0000</pCOFINS><vCOFINS>5.72</vCOFINS></COFINSAliq></COFINS></imposto></det><det nItem="24"><prod><cProd>12838</cProd><cEAN>7896383073891</cEAN><xProd>COLORETI TRADICIONAL 20X300G 20X300G QTD. 1.00 CX</xProd><NCM>18069000</NCM><CEST>1700900</CEST><indEscala>S</indEscala><CFOP>5403</CFOP><uCom>UN</uCom><qCom>20.0000</qCom><vUnCom>8.3945000000</vUnCom><vProd>167.89</vProd><cEANTrib>7896383073891</cEANTrib><uTrib>UN</uTrib><qTrib>20.0000</qTrib><vUnTrib>8.3945000000</vUnTrib><indTot>1</indTot><xPed>645000391</xPed><nItemPed>26</nItemPed></prod><imposto><ICMS><ICMS60><orig>0</orig><CST>60</CST><vBCSTRet>115.70</vBCSTRet><pST>18.0000</pST><vICMSSubstituto>0.00</vICMSSubstituto><vICMSSTRet>14.60</vICMSSTRet></ICMS60></ICMS><IPI><cEnq>999</cEnq><IPITrib><CST>99</CST><vBC>0.00</vBC><pIPI>0.0000</pIPI><vIPI>0.00</vIPI></IPITrib></IPI><PIS><PISAliq><CST>01</CST><vBC>167.89</vBC><pPIS>0.6500</pPIS><vPIS>1.09</vPIS></PISAliq></PIS><COFINS><COFINSAliq><CST>01</CST><vBC>167.89</vBC><pCOFINS>3.0000</pCOFINS><vCOFINS>5.04</vCOFINS></COFINSAliq></COFINS></imposto></det><det nItem="25"><prod><cProd>48407</cProd><cEAN>7898656683271</cEAN><xProd>CONFEITO PIROMANIA DP C/15UN 15X1UN QTD. 12.00 DP</xProd><NCM>17049020</NCM><CEST>2804100</CEST><indEscala>S</indEscala><CFOP>5102</CFOP><uCom>UN</uCom><qCom>180.0000</qCom><vUnCom>2.1557777778</vUnCom><vProd>388.04</vProd><cEANTrib>7898656683271</cEANTrib><uTrib>UN</uTrib><qTrib>180.0000</qTrib><vUnTrib>2.1557777778</vUnTrib><indTot>1</indTot><xPed>645000391</xPed><nItemPed>27</nItemPed></prod><imposto><vTotTrib>77.61</vTotTrib><ICMS><ICMS00><orig>0</orig><CST>00</CST><modBC>3</modBC><vBC>388.04</vBC><pICMS>20.0000</pICMS><vICMS>77.61</vICMS></ICMS00></ICMS><IPI><cEnq>999</cEnq><IPITrib><CST>99</CST><vBC>0.00</vBC><pIPI>0.0000</pIPI><vIPI>0.00</vIPI></IPITrib></IPI><PIS><PISAliq><CST>01</CST><vBC>388.04</vBC><pPIS>0.6500</pPIS><vPIS>2.52</vPIS></PISAliq></PIS><COFINS><COFINSAliq><CST>01</CST><vBC>388.04</vBC><pCOFINS>3.0000</pCOFINS><vCOFINS>11.64</vCOFINS></COFINSAliq></COFINS></imposto></det><det nItem="26"><prod><cProd>59081</cProd><cEAN>7890000590815</cEAN><xProd>COPO DE VIDRO AMERICANO 190ML CX-24X1UN QTD. 30.00 UN</xProd><NCM>70133700</NCM><CFOP>5403</CFOP><uCom>UN</uCom><qCom>720.0000</qCom><vUnCom>1.3184027778</vUnCom><vProd>949.25</vProd><cEANTrib>7891155003663</cEANTrib><uTrib>UN</uTrib><qTrib>720.0000</qTrib><vUnTrib>1.3184027778</vUnTrib><indTot>1</indTot><xPed>645000391</xPed><nItemPed>28</nItemPed><nFCI>B5D64726-5B48-43C0-844F-6666C1D96C39</nFCI></prod><imposto><ICMS><ICMS60><orig>5</orig><CST>60</CST><vBCSTRet>877.48</vBCSTRet><pST>20.0000</pST><vICMSSubstituto>29.94</vICMSSubstituto><vICMSSTRet>133.94</vICMSSTRet></ICMS60></ICMS><IPI><cEnq>999</cEnq><IPITrib><CST>99</CST><vBC>0.00</vBC><pIPI>0.0000</pIPI><vIPI>0.00</vIPI></IPITrib></IPI><PIS><PISAliq><CST>01</CST><vBC>949.25</vBC><pPIS>0.6500</pPIS><vPIS>6.17</vPIS></PISAliq></PIS><COFINS><COFINSAliq><CST>01</CST><vBC>949.25</vBC><pCOFINS>3.0000</pCOFINS><vCOFINS>28.48</vCOFINS></COFINSAliq></COFINS></imposto><infAdProd>PERC.PARC.FCI: 0 - N. FCI: B5D64726-5B48-43C0-844F-6666C1D96C39</infAdProd></det><det nItem="27"><prod><cProd>13411</cProd><cEAN>7898279790394</cEAN><xProd>GELATINAS FINI BANANAS12X90G 12X90G QTD. 1.00 CX</xProd><NCM>17049020</NCM><CEST>2804100</CEST><indEscala>S</indEscala><CFOP>5102</CFOP><uCom>PC</uCom><qCom>12.0000</qCom><vUnCom>7.3108333333</vUnCom><vProd>87.73</vProd><cEANTrib>7898279790394</cEANTrib><uTrib>PC</uTrib><qTrib>12.0000</qTrib><vUnTrib>7.3108333333</vUnTrib><indTot>1</indTot><xPed>645000391</xPed><nItemPed>29</nItemPed></prod><imposto><vTotTrib>17.55</vTotTrib><ICMS><ICMS00><orig>0</orig><CST>00</CST><modBC>3</modBC><vBC>87.73</vBC><pICMS>20.0000</pICMS><vICMS>17.55</vICMS></ICMS00></ICMS><IPI><cEnq>999</cEnq><IPITrib><CST>99</CST><vBC>0.00</vBC><pIPI>0.0000</pIPI><vIPI>0.00</vIPI></IPITrib></IPI><PIS><PISAliq><CST>01</CST><vBC>87.73</vBC><pPIS>0.6500</pPIS><vPIS>0.57</vPIS></PISAliq></PIS><COFINS><COFINSAliq><CST>01</CST><vBC>87.73</vBC><pCOFINS>3.0000</pCOFINS><vCOFINS>2.63</vCOFINS></COFINSAliq></COFINS></imposto></det><det nItem="28"><prod><cProd>13619</cProd><cEAN>7898279790400</cEAN><xProd>GELATINAS FINI BEIJO MORANGO 12X90G 12X100G QTD. 1.00 CX</xProd><NCM>17049020</NCM><CEST>2804100</CEST><indEscala>S</indEscala><CFOP>5102</CFOP><uCom>PC</uCom><qCom>12.0000</qCom><vUnCom>7.3108333333</vUnCom><vProd>87.73</vProd><cEANTrib>7898279790400</cEANTrib><uTrib>PC</uTrib><qTrib>12.0000</qTrib><vUnTrib>7.3108333333</vUnTrib><indTot>1</indTot><xPed>645000391</xPed><nItemPed>30</nItemPed></prod><imposto><vTotTrib>17.55</vTotTrib><ICMS><ICMS00><orig>0</orig><CST>00</CST><modBC>3</modBC><vBC>87.73</vBC><pICMS>20.0000</pICMS><vICMS>17.55</vICMS></ICMS00></ICMS><IPI><cEnq>999</cEnq><IPITrib><CST>99</CST><vBC>0.00</vBC><pIPI>0.0000</pIPI><vIPI>0.00</vIPI></IPITrib></IPI><PIS><PISAliq><CST>01</CST><vBC>87.73</vBC><pPIS>0.6500</pPIS><vPIS>0.57</vPIS></PISAliq></PIS><COFINS><COFINSAliq><CST>01</CST><vBC>87.73</vBC><pCOFINS>3.0000</pCOFINS><vCOFINS>2.63</vCOFINS></COFINSAliq></COFINS></imposto></det><det nItem="29"><prod><cProd>13412</cProd><cEAN>7898279790417</cEAN><xProd>GELATINAS FINI DENTADURAS 12X90G 12X90G QTD. 1.00 CX</xProd><NCM>17049020</NCM><CEST>2804100</CEST><indEscala>S</indEscala><CFOP>5102</CFOP><uCom>PC</uCom><qCom>12.0000</qCom><vUnCom>7.3108333333</vUnCom><vProd>87.73</vProd><cEANTrib>7898279790417</cEANTrib><uTrib>PC</uTrib><qTrib>12.0000</qTrib><vUnTrib>7.3108333333</vUnTrib><indTot>1</indTot><xPed>645000391</xPed><nItemPed>31</nItemPed></prod><imposto><vTotTrib>17.55</vTotTrib><ICMS><ICMS00><orig>0</orig><CST>00</CST><modBC>3</modBC><vBC>87.73</vBC><pICMS>20.0000</pICMS><vICMS>17.55</vICMS></ICMS00></ICMS><IPI><cEnq>999</cEnq><IPITrib><CST>99</CST><vBC>0.00</vBC><pIPI>0.0000</pIPI><vIPI>0.00</vIPI></IPITrib></IPI><PIS><PISAliq><CST>01</CST><vBC>87.73</vBC><pPIS>0.6500</pPIS><vPIS>0.57</vPIS></PISAliq></PIS><COFINS><COFINSAliq><CST>01</CST><vBC>87.73</vBC><pCOFINS>3.0000</pCOFINS><vCOFINS>2.63</vCOFINS></COFINSAliq></COFINS></imposto></det><det nItem="30"><prod><cProd>12594</cProd><cEAN>7896058517422</cEAN><xProd>GOMETS GOMA TUBO CREME FRUTAS 12X30X32G 12X30X32G QTD. 5.00 CX</xProd><NCM>17049020</NCM><CEST>2804100</CEST><indEscala>S</indEscala><CFOP>5102</CFOP><uCom>DP</uCom><qCom>60.0000</qCom><vUnCom>14.9350000000</vUnCom><vProd>896.10</vProd><cEANTrib>7896058517422</cEANTrib><uTrib>DP</uTrib><qTrib>60.0000</qTrib><vUnTrib>14.9350000000</vUnTrib><indTot>1</indTot><xPed>645000391</xPed><nItemPed>32</nItemPed></prod><imposto><vTotTrib>179.22</vTotTrib><ICMS><ICMS00><orig>0</orig><CST>00</CST><modBC>3</modBC><vBC>896.10</vBC><pICMS>20.0000</pICMS><vICMS>179.22</vICMS></ICMS00></ICMS><IPI><cEnq>999</cEnq><IPITrib><CST>99</CST><vBC>0.00</vBC><pIPI>0.0000</pIPI><vIPI>0.00</vIPI></IPITrib></IPI><PIS><PISAliq><CST>01</CST><vBC>896.10</vBC><pPIS>0.6500</pPIS><vPIS>5.82</vPIS></PISAliq></PIS><COFINS><COFINSAliq><CST>01</CST><vBC>896.10</vBC><pCOFINS>3.0000</pCOFINS><vCOFINS>26.88</vCOFINS></COFINSAliq></COFINS></imposto></det><det nItem="31"><prod><cProd>5239</cProd><cEAN>07896058516104</cEAN><xProd>GOMETS GOMA TUBO FRUTAS SORT 12X30X32G 12X30UNX32G QTD. 10.00 CX</xProd><NCM>17049020</NCM><CEST>2804100</CEST><indEscala>S</indEscala><CFOP>5102</CFOP><uCom>DP</uCom><qCom>120.0000</qCom><vUnCom>14.9350000000</vUnCom><vProd>1792.20</vProd><cEANTrib>07896058516104</cEANTrib><uTrib>DP</uTrib><qTrib>120.0000</qTrib><vUnTrib>14.9350000000</vUnTrib><indTot>1</indTot><xPed>645000391</xPed><nItemPed>33</nItemPed></prod><imposto><vTotTrib>358.44</vTotTrib><ICMS><ICMS00><orig>0</orig><CST>00</CST><modBC>3</modBC><vBC>1792.20</vBC><pICMS>20.0000</pICMS><vICMS>358.44</vICMS></ICMS00></ICMS><IPI><cEnq>999</cEnq><IPITrib><CST>99</CST><vBC>0.00</vBC><pIPI>0.0000</pIPI><vIPI>0.00</vIPI></IPITrib></IPI><PIS><PISAliq><CST>01</CST><vBC>1792.20</vBC><pPIS>0.6500</pPIS><vPIS>11.65</vPIS></PISAliq></PIS><COFINS><COFINSAliq><CST>01</CST><vBC>1792.20</vBC><pCOFINS>3.0000</pCOFINS><vCOFINS>53.77</vCOFINS></COFINSAliq></COFINS></imposto></det><det nItem="32"><prod><cProd>45815</cProd><cEAN>7896058597905</cEAN><xProd>GOMETS SINO CARTELADO 12X5X24G 12X5X30G QTD. 2.00 CX</xProd><NCM>17049020</NCM><CEST>2804100</CEST><indEscala>S</indEscala><CFOP>5102</CFOP><uCom>CT</uCom><qCom>24.0000</qCom><vUnCom>3.4212500000</vUnCom><vProd>82.11</vProd><cEANTrib>7896058597905</cEANTrib><uTrib>CT</uTrib><qTrib>24.0000</qTrib><vUnTrib>3.4212500000</vUnTrib><indTot>1</indTot><xPed>645000391</xPed><nItemPed>34</nItemPed></prod><imposto><vTotTrib>16.42</vTotTrib><ICMS><ICMS00><orig>0</orig><CST>00</CST><modBC>3</modBC><vBC>82.11</vBC><pICMS>20.0000</pICMS><vICMS>16.42</vICMS></ICMS00></ICMS><IPI><cEnq>999</cEnq><IPITrib><CST>99</CST><vBC>0.00</vBC><pIPI>0.0000</pIPI><vIPI>0.00</vIPI></IPITrib></IPI><PIS><PISAliq><CST>01</CST><vBC>82.11</vBC><pPIS>0.6500</pPIS><vPIS>0.53</vPIS></PISAliq></PIS><COFINS><COFINSAliq><CST>01</CST><vBC>82.11</vBC><pCOFINS>3.0000</pCOFINS><vCOFINS>2.46</vCOFINS></COFINSAliq></COFINS></imposto></det><det nItem="33"><prod><cProd>40056</cProd><cEAN>7898591459436</cEAN><xProd>MARSHMALLOW ALVORADA CB 12X250G 250G QTD. 12.00 PC</xProd><NCM>17049020</NCM><CEST>2804100</CEST><indEscala>S</indEscala><CFOP>5102</CFOP><uCom>PC</uCom><qCom>12.0000</qCom><vUnCom>8.4825000000</vUnCom><vProd>101.79</vProd><cEANTrib>7898591459436</cEANTrib><uTrib>PC</uTrib><qTrib>12.0000</qTrib><vUnTrib>8.4825000000</vUnTrib><indTot>1</indTot><xPed>645000391</xPed><nItemPed>35</nItemPed></prod><imposto><vTotTrib>20.36</vTotTrib><ICMS><ICMS00><orig>0</orig><CST>00</CST><modBC>3</modBC><vBC>101.79</vBC><pICMS>20.0000</pICMS><vICMS>20.36</vICMS></ICMS00></ICMS><IPI><cEnq>999</cEnq><IPITrib><CST>99</CST><vBC>0.00</vBC><pIPI>0.0000</pIPI><vIPI>0.00</vIPI></IPITrib></IPI><PIS><PISAliq><CST>01</CST><vBC>101.79</vBC><pPIS>0.6500</pPIS><vPIS>0.66</vPIS></PISAliq></PIS><COFINS><COFINSAliq><CST>01</CST><vBC>101.79</vBC><pCOFINS>3.0000</pCOFINS><vCOFINS>3.05</vCOFINS></COFINSAliq></COFINS></imposto></det><det nItem="34"><prod><cProd>13266</cProd><cEAN>7898591450150</cEAN><xProd>MARSHMALLOW BORBOLETA 12X250G 12X250G QTD. 1.00 CX</xProd><NCM>17049020</NCM><CEST>2804100</CEST><indEscala>S</indEscala><CFOP>5102</CFOP><uCom>PC</uCom><qCom>12.0000</qCom><vUnCom>8.4825000000</vUnCom><vProd>101.79</vProd><cEANTrib>7898591450150</cEANTrib><uTrib>PC</uTrib><qTrib>12.0000</qTrib><vUnTrib>8.4825000000</vUnTrib><indTot>1</indTot><xPed>645000391</xPed><nItemPed>36</nItemPed></prod><imposto><vTotTrib>20.36</vTotTrib><ICMS><ICMS00><orig>0</orig><CST>00</CST><modBC>3</modBC><vBC>101.79</vBC><pICMS>20.0000</pICMS><vICMS>20.36</vICMS></ICMS00></ICMS><IPI><cEnq>999</cEnq><IPITrib><CST>99</CST><vBC>0.00</vBC><pIPI>0.0000</pIPI><vIPI>0.00</vIPI></IPITrib></IPI><PIS><PISAliq><CST>01</CST><vBC>101.79</vBC><pPIS>0.6500</pPIS><vPIS>0.66</vPIS></PISAliq></PIS><COFINS><COFINSAliq><CST>01</CST><vBC>101.79</vBC><pCOFINS>3.0000</pCOFINS><vCOFINS>3.05</vCOFINS></COFINSAliq></COFINS></imposto></det><det nItem="35"><prod><cProd>41458</cProd><cEAN>7898591459818</cEAN><xProd>MARSHMALLOW CORACAO 12X250G 12X250G QTD. 1.00 CX</xProd><NCM>17049020</NCM><CEST>2804100</CEST><indEscala>S</indEscala><CFOP>5102</CFOP><uCom>PC</uCom><qCom>12.0000</qCom><vUnCom>8.4825000000</vUnCom><vProd>101.79</vProd><cEANTrib>7898591459818</cEANTrib><uTrib>PC</uTrib><qTrib>12.0000</qTrib><vUnTrib>8.4825000000</vUnTrib><indTot>1</indTot><xPed>645000391</xPed><nItemPed>37</nItemPed></prod><imposto><vTotTrib>20.36</vTotTrib><ICMS><ICMS00><orig>0</orig><CST>00</CST><modBC>3</modBC><vBC>101.79</vBC><pICMS>20.0000</pICMS><vICMS>20.36</vICMS></ICMS00></ICMS><IPI><cEnq>999</cEnq><IPITrib><CST>99</CST><vBC>0.00</vBC><pIPI>0.0000</pIPI><vIPI>0.00</vIPI></IPITrib></IPI><PIS><PISAliq><CST>01</CST><vBC>101.79</vBC><pPIS>0.6500</pPIS><vPIS>0.66</vPIS></PISAliq></PIS><COFINS><COFINSAliq><CST>01</CST><vBC>101.79</vBC><pCOFINS>3.0000</pCOFINS><vCOFINS>3.05</vCOFINS></COFINSAliq></COFINS></imposto></det><det nItem="36"><prod><cProd>40057</cProd><cEAN>7898591459429</cEAN><xProd>MARSHMALLOW FLOR CB 12X250G 250G QTD. 12.00 PC</xProd><NCM>17049020</NCM><CEST>2804100</CEST><indEscala>S</indEscala><CFOP>5102</CFOP><uCom>PC</uCom><qCom>12.0000</qCom><vUnCom>8.4825000000</vUnCom><vProd>101.79</vProd><cEANTrib>7898591459429</cEANTrib><uTrib>PC</uTrib><qTrib>12.0000</qTrib><vUnTrib>8.4825000000</vUnTrib><indTot>1</indTot><xPed>645000391</xPed><nItemPed>38</nItemPed></prod><imposto><vTotTrib>20.36</vTotTrib><ICMS><ICMS00><orig>0</orig><CST>00</CST><modBC>3</modBC><vBC>101.79</vBC><pICMS>20.0000</pICMS><vICMS>20.36</vICMS></ICMS00></ICMS><IPI><cEnq>999</cEnq><IPITrib><CST>99</CST><vBC>0.00</vBC><pIPI>0.0000</pIPI><vIPI>0.00</vIPI></IPITrib></IPI><PIS><PISAliq><CST>01</CST><vBC>101.79</vBC><pPIS>0.6500</pPIS><vPIS>0.66</vPIS></PISAliq></PIS><COFINS><COFINSAliq><CST>01</CST><vBC>101.79</vBC><pCOFINS>3.0000</pCOFINS><vCOFINS>3.05</vCOFINS></COFINSAliq></COFINS></imposto></det><det nItem="37"><prod><cProd>13272</cProd><cEAN>7898519450071</cEAN><xProd>MARSHMALLOW MORANGO 12X250G 12X250G QTD. 1.00 CX</xProd><NCM>17049020</NCM><CEST>2804100</CEST><indEscala>S</indEscala><CFOP>5102</CFOP><uCom>PC</uCom><qCom>12.0000</qCom><vUnCom>8.4825000000</vUnCom><vProd>101.79</vProd><cEANTrib>7898519450071</cEANTrib><uTrib>PC</uTrib><qTrib>12.0000</qTrib><vUnTrib>8.4825000000</vUnTrib><indTot>1</indTot><xPed>645000391</xPed><nItemPed>39</nItemPed></prod><imposto><vTotTrib>20.36</vTotTrib><ICMS><ICMS00><orig>0</orig><CST>00</CST><modBC>3</modBC><vBC>101.79</vBC><pICMS>20.0000</pICMS><vICMS>20.36</vICMS></ICMS00></ICMS><IPI><cEnq>999</cEnq><IPITrib><CST>99</CST><vBC>0.00</vBC><pIPI>0.0000</pIPI><vIPI>0.00</vIPI></IPITrib></IPI><PIS><PISAliq><CST>01</CST><vBC>101.79</vBC><pPIS>0.6500</pPIS><vPIS>0.66</vPIS></PISAliq></PIS><COFINS><COFINSAliq><CST>01</CST><vBC>101.79</vBC><pCOFINS>3.0000</pCOFINS><vCOFINS>3.05</vCOFINS></COFINSAliq></COFINS></imposto></det><det nItem="38"><prod><cProd>14613</cProd><cEAN>7898591454592</cEAN><xProd>MARSHMALLOW P/ ASSAR CAMPING 12X250G 12X250G QTD. 1.00 CX</xProd><NCM>17049020</NCM><CEST>2804100</CEST><indEscala>S</indEscala><CFOP>5102</CFOP><uCom>PC</uCom><qCom>12.0000</qCom><vUnCom>8.4825000000</vUnCom><vProd>101.79</vProd><cEANTrib>7898591454592</cEANTrib><uTrib>PC</uTrib><qTrib>12.0000</qTrib><vUnTrib>8.4825000000</vUnTrib><indTot>1</indTot><xPed>645000391</xPed><nItemPed>40</nItemPed></prod><imposto><vTotTrib>20.36</vTotTrib><ICMS><ICMS00><orig>0</orig><CST>00</CST><modBC>3</modBC><vBC>101.79</vBC><pICMS>20.0000</pICMS><vICMS>20.36</vICMS></ICMS00></ICMS><IPI><cEnq>999</cEnq><IPITrib><CST>99</CST><vBC>0.00</vBC><pIPI>0.0000</pIPI><vIPI>0.00</vIPI></IPITrib></IPI><PIS><PISAliq><CST>01</CST><vBC>101.79</vBC><pPIS>0.6500</pPIS><vPIS>0.66</vPIS></PISAliq></PIS><COFINS><COFINSAliq><CST>01</CST><vBC>101.79</vBC><pCOFINS>3.0000</pCOFINS><vCOFINS>3.05</vCOFINS></COFINSAliq></COFINS></imposto></det><det nItem="39"><prod><cProd>48677</cProd><cEAN>07908228802419</cEAN><xProd>MARSHMALLOW RECH AZUL/BRANCO 12X250G 12X250G QTD. 1.00 CX</xProd><NCM>17049020</NCM><CEST>2804100</CEST><indEscala>S</indEscala><CFOP>5102</CFOP><uCom>PC</uCom><qCom>12.0000</qCom><vUnCom>8.4825000000</vUnCom><vProd>101.79</vProd><cEANTrib>07908228802419</cEANTrib><uTrib>PC</uTrib><qTrib>12.0000</qTrib><vUnTrib>8.4825000000</vUnTrib><indTot>1</indTot><xPed>645000391</xPed><nItemPed>41</nItemPed></prod><imposto><vTotTrib>20.36</vTotTrib><ICMS><ICMS00><orig>0</orig><CST>00</CST><modBC>3</modBC><vBC>101.79</vBC><pICMS>20.0000</pICMS><vICMS>20.36</vICMS></ICMS00></ICMS><IPI><cEnq>999</cEnq><IPITrib><CST>99</CST><vBC>0.00</vBC><pIPI>0.0000</pIPI><vIPI>0.00</vIPI></IPITrib></IPI><PIS><PISAliq><CST>01</CST><vBC>101.79</vBC><pPIS>0.6500</pPIS><vPIS>0.66</vPIS></PISAliq></PIS><COFINS><COFINSAliq><CST>01</CST><vBC>101.79</vBC><pCOFINS>3.0000</pCOFINS><vCOFINS>3.05</vCOFINS></COFINSAliq></COFINS></imposto></det><det nItem="40"><prod><cProd>48678</cProd><cEAN>07908228802402</cEAN><xProd>MARSHMALLOW RECH ROSA/BRANCO 12X250G 12X250G QTD. 1.00 CX</xProd><NCM>17049020</NCM><CEST>2804100</CEST><indEscala>S</indEscala><CFOP>5102</CFOP><uCom>PC</uCom><qCom>12.0000</qCom><vUnCom>8.4825000000</vUnCom><vProd>101.79</vProd><cEANTrib>07908228802402</cEANTrib><uTrib>PC</uTrib><qTrib>12.0000</qTrib><vUnTrib>8.4825000000</vUnTrib><indTot>1</indTot><xPed>645000391</xPed><nItemPed>42</nItemPed></prod><imposto><vTotTrib>20.36</vTotTrib><ICMS><ICMS00><orig>0</orig><CST>00</CST><modBC>3</modBC><vBC>101.79</vBC><pICMS>20.0000</pICMS><vICMS>20.36</vICMS></ICMS00></ICMS><IPI><cEnq>999</cEnq><IPITrib><CST>99</CST><vBC>0.00</vBC><pIPI>0.0000</pIPI><vIPI>0.00</vIPI></IPITrib></IPI><PIS><PISAliq><CST>01</CST><vBC>101.79</vBC><pPIS>0.6500</pPIS><vPIS>0.66</vPIS></PISAliq></PIS><COFINS><COFINSAliq><CST>01</CST><vBC>101.79</vBC><pCOFINS>3.0000</pCOFINS><vCOFINS>3.05</vCOFINS></COFINSAliq></COFINS></imposto></det><det nItem="41"><prod><cProd>48679</cProd><cEAN>07908228802426</cEAN><xProd>MARSHMALLOW RECH TORCAO 12X250G 12X250G QTD. 1.00 CX</xProd><NCM>17049020</NCM><CEST>2804100</CEST><indEscala>S</indEscala><CFOP>5102</CFOP><uCom>PC</uCom><qCom>12.0000</qCom><vUnCom>8.4825000000</vUnCom><vProd>101.79</vProd><cEANTrib>07908228802426</cEANTrib><uTrib>PC</uTrib><qTrib>12.0000</qTrib><vUnTrib>8.4825000000</vUnTrib><indTot>1</indTot><xPed>645000391</xPed><nItemPed>43</nItemPed></prod><imposto><vTotTrib>20.36</vTotTrib><ICMS><ICMS00><orig>0</orig><CST>00</CST><modBC>3</modBC><vBC>101.79</vBC><pICMS>20.0000</pICMS><vICMS>20.36</vICMS></ICMS00></ICMS><IPI><cEnq>999</cEnq><IPITrib><CST>99</CST><vBC>0.00</vBC><pIPI>0.0000</pIPI><vIPI>0.00</vIPI></IPITrib></IPI><PIS><PISAliq><CST>01</CST><vBC>101.79</vBC><pPIS>0.6500</pPIS><vPIS>0.66</vPIS></PISAliq></PIS><COFINS><COFINSAliq><CST>01</CST><vBC>101.79</vBC><pCOFINS>3.0000</pCOFINS><vCOFINS>3.05</vCOFINS></COFINSAliq></COFINS></imposto></det><det nItem="42"><prod><cProd>13427</cProd><cEAN>7898279791162</cEAN><xProd>MARSHMALLOW TORCAO 12X80G 12X80G QTD. 1.00 CX</xProd><NCM>17049020</NCM><CEST>2804100</CEST><indEscala>S</indEscala><CFOP>5102</CFOP><uCom>PC</uCom><qCom>12.0000</qCom><vUnCom>7.3108333333</vUnCom><vProd>87.73</vProd><cEANTrib>7898279791162</cEANTrib><uTrib>PC</uTrib><qTrib>12.0000</qTrib><vUnTrib>7.3108333333</vUnTrib><indTot>1</indTot><xPed>645000391</xPed><nItemPed>44</nItemPed></prod><imposto><vTotTrib>17.55</vTotTrib><ICMS><ICMS00><orig>0</orig><CST>00</CST><modBC>3</modBC><vBC>87.73</vBC><pICMS>20.0000</pICMS><vICMS>17.55</vICMS></ICMS00></ICMS><IPI><cEnq>999</cEnq><IPITrib><CST>99</CST><vBC>0.00</vBC><pIPI>0.0000</pIPI><vIPI>0.00</vIPI></IPITrib></IPI><PIS><PISAliq><CST>01</CST><vBC>87.73</vBC><pPIS>0.6500</pPIS><vPIS>0.57</vPIS></PISAliq></PIS><COFINS><COFINSAliq><CST>01</CST><vBC>87.73</vBC><pCOFINS>3.0000</pCOFINS><vCOFINS>2.63</vCOFINS></COFINSAliq></COFINS></imposto></det><det nItem="43"><prod><cProd>14036</cProd><cEAN>7898591453793</cEAN><xProd>MARSHMALLOW TORCAO AZUL 12X250G 250G QTD. 12.00 PC</xProd><NCM>17049020</NCM><CEST>2804100</CEST><indEscala>S</indEscala><CFOP>5102</CFOP><uCom>PC</uCom><qCom>12.0000</qCom><vUnCom>8.4825000000</vUnCom><vProd>101.79</vProd><cEANTrib>7898591453793</cEANTrib><uTrib>PC</uTrib><qTrib>12.0000</qTrib><vUnTrib>8.4825000000</vUnTrib><indTot>1</indTot><xPed>645000391</xPed><nItemPed>45</nItemPed></prod><imposto><vTotTrib>20.36</vTotTrib><ICMS><ICMS00><orig>0</orig><CST>00</CST><modBC>3</modBC><vBC>101.79</vBC><pICMS>20.0000</pICMS><vICMS>20.36</vICMS></ICMS00></ICMS><IPI><cEnq>999</cEnq><IPITrib><CST>99</CST><vBC>0.00</vBC><pIPI>0.0000</pIPI><vIPI>0.00</vIPI></IPITrib></IPI><PIS><PISAliq><CST>01</CST><vBC>101.79</vBC><pPIS>0.6500</pPIS><vPIS>0.66</vPIS></PISAliq></PIS><COFINS><COFINSAliq><CST>01</CST><vBC>101.79</vBC><pCOFINS>3.0000</pCOFINS><vCOFINS>3.05</vCOFINS></COFINSAliq></COFINS></imposto></det><det nItem="44"><prod><cProd>14008</cProd><cEAN>7898591453809</cEAN><xProd>MARSHMALLOW TORCAO BRANCO 12X250G 12X250G QTD. 1.00 CX</xProd><NCM>17049020</NCM><CEST>2804100</CEST><indEscala>S</indEscala><CFOP>5102</CFOP><uCom>PC</uCom><qCom>12.0000</qCom><vUnCom>8.4825000000</vUnCom><vProd>101.79</vProd><cEANTrib>7898591453809</cEANTrib><uTrib>PC</uTrib><qTrib>12.0000</qTrib><vUnTrib>8.4825000000</vUnTrib><indTot>1</indTot><xPed>645000391</xPed><nItemPed>46</nItemPed></prod><imposto><vTotTrib>20.36</vTotTrib><ICMS><ICMS00><orig>0</orig><CST>00</CST><modBC>3</modBC><vBC>101.79</vBC><pICMS>20.0000</pICMS><vICMS>20.36</vICMS></ICMS00></ICMS><IPI><cEnq>999</cEnq><IPITrib><CST>99</CST><vBC>0.00</vBC><pIPI>0.0000</pIPI><vIPI>0.00</vIPI></IPITrib></IPI><PIS><PISAliq><CST>01</CST><vBC>101.79</vBC><pPIS>0.6500</pPIS><vPIS>0.66</vPIS></PISAliq></PIS><COFINS><COFINSAliq><CST>01</CST><vBC>101.79</vBC><pCOFINS>3.0000</pCOFINS><vCOFINS>3.05</vCOFINS></COFINSAliq></COFINS></imposto></det><det nItem="45"><prod><cProd>40060</cProd><cEAN>7898591459405</cEAN><xProd>MARSHMALLOW TORCAO CB 12X250G 250G QTD. 12.00 PC</xProd><NCM>17049020</NCM><CEST>2804100</CEST><indEscala>S</indEscala><CFOP>5102</CFOP><uCom>PC</uCom><qCom>12.0000</qCom><vUnCom>8.4825000000</vUnCom><vProd>101.79</vProd><cEANTrib>7898591459405</cEANTrib><uTrib>PC</uTrib><qTrib>12.0000</qTrib><vUnTrib>8.4825000000</vUnTrib><indTot>1</indTot><xPed>645000391</xPed><nItemPed>47</nItemPed></prod><imposto><vTotTrib>20.36</vTotTrib><ICMS><ICMS00><orig>0</orig><CST>00</CST><modBC>3</modBC><vBC>101.79</vBC><pICMS>20.0000</pICMS><vICMS>20.36</vICMS></ICMS00></ICMS><IPI><cEnq>999</cEnq><IPITrib><CST>99</CST><vBC>0.00</vBC><pIPI>0.0000</pIPI><vIPI>0.00</vIPI></IPITrib></IPI><PIS><PISAliq><CST>01</CST><vBC>101.79</vBC><pPIS>0.6500</pPIS><vPIS>0.66</vPIS></PISAliq></PIS><COFINS><COFINSAliq><CST>01</CST><vBC>101.79</vBC><pCOFINS>3.0000</pCOFINS><vCOFINS>3.05</vCOFINS></COFINSAliq></COFINS></imposto></det><det nItem="46"><prod><cProd>14614</cProd><cEAN>7898591454844</cEAN><xProd>MARSHMALLOW TORCAO ROSA 12X250G 12X250G QTD. 1.00 CX</xProd><NCM>17049020</NCM><CEST>2804100</CEST><indEscala>S</indEscala><CFOP>5102</CFOP><uCom>PC</uCom><qCom>12.0000</qCom><vUnCom>8.4825000000</vUnCom><vProd>101.79</vProd><cEANTrib>7898591454844</cEANTrib><uTrib>PC</uTrib><qTrib>12.0000</qTrib><vUnTrib>8.4825000000</vUnTrib><indTot>1</indTot><xPed>645000391</xPed><nItemPed>48</nItemPed></prod><imposto><vTotTrib>20.36</vTotTrib><ICMS><ICMS00><orig>0</orig><CST>00</CST><modBC>3</modBC><vBC>101.79</vBC><pICMS>20.0000</pICMS><vICMS>20.36</vICMS></ICMS00></ICMS><IPI><cEnq>999</cEnq><IPITrib><CST>99</CST><vBC>0.00</vBC><pIPI>0.0000</pIPI><vIPI>0.00</vIPI></IPITrib></IPI><PIS><PISAliq><CST>01</CST><vBC>101.79</vBC><pPIS>0.6500</pPIS><vPIS>0.66</vPIS></PISAliq></PIS><COFINS><COFINSAliq><CST>01</CST><vBC>101.79</vBC><pCOFINS>3.0000</pCOFINS><vCOFINS>3.05</vCOFINS></COFINSAliq></COFINS></imposto></det><det nItem="47"><prod><cProd>58860</cProd><cEAN>7898094764396</cEAN><xProd>MOEDAS AO LEITE KIKAKAU 16X500G 500G QTD. 16.00 PT</xProd><NCM>18063220</NCM><CFOP>5403</CFOP><uCom>PT</uCom><qCom>16.0000</qCom><vUnCom>41.6631250000</vUnCom><vProd>666.61</vProd><cEANTrib>7898094764396</cEANTrib><uTrib>PT</uTrib><qTrib>16.0000</qTrib><vUnTrib>41.6631250000</vUnTrib><indTot>1</indTot><xPed>645000391</xPed><nItemPed>49</nItemPed></prod><imposto><ICMS><ICMS60><orig>0</orig><CST>60</CST><vBCSTRet>453.35</vBCSTRet><pST>18.0000</pST><vICMSSubstituto>0.00</vICMSSubstituto><vICMSSTRet>57.22</vICMSSTRet></ICMS60></ICMS><IPI><cEnq>999</cEnq><IPITrib><CST>99</CST><vBC>0.00</vBC><pIPI>0.0000</pIPI><vIPI>0.00</vIPI></IPITrib></IPI><PIS><PISAliq><CST>01</CST><vBC>666.61</vBC><pPIS>0.6500</pPIS><vPIS>4.33</vPIS></PISAliq></PIS><COFINS><COFINSAliq><CST>01</CST><vBC>666.61</vBC><pCOFINS>3.0000</pCOFINS><vCOFINS>20.00</vCOFINS></COFINSAliq></COFINS></imposto></det><det nItem="48"><prod><cProd>56392</cProd><cEAN>7896202892115</cEAN><xProd>PALMITO PUPUNHA TOLETE 15X300G 300G QTD. 5.00 PT</xProd><NCM>20089100</NCM><CFOP>5403</CFOP><uCom>PT</uCom><qCom>5.0000</qCom><vUnCom>18.0440000000</vUnCom><vProd>90.22</vProd><cEANTrib>7896202892115</cEANTrib><uTrib>PT</uTrib><qTrib>5.0000</qTrib><vUnTrib>18.0440000000</vUnTrib><indTot>1</indTot><xPed>645000391</xPed><nItemPed>50</nItemPed></prod><imposto><ICMS><ICMS60><orig>0</orig><CST>60</CST><vBCSTRet>60.35</vBCSTRet><pST>18.0000</pST><vICMSSubstituto>0.00</vICMSSubstituto><vICMSSTRet>7.64</vICMSSTRet></ICMS60></ICMS><IPI><cEnq>999</cEnq><IPITrib><CST>99</CST><vBC>0.00</vBC><pIPI>0.0000</pIPI><vIPI>0.00</vIPI></IPITrib></IPI><PIS><PISAliq><CST>01</CST><vBC>90.22</vBC><pPIS>0.6500</pPIS><vPIS>0.59</vPIS></PISAliq></PIS><COFINS><COFINSAliq><CST>01</CST><vBC>90.22</vBC><pCOFINS>3.0000</pCOFINS><vCOFINS>2.71</vCOFINS></COFINSAliq></COFINS></imposto></det><det nItem="49"><prod><cProd>43224</cProd><cEAN>7897426020698</cEAN><xProd>PAO DE MEL SAGRA C/COB. CHOCO BRANCO 60G 30X60G QTD. 1.00 CX</xProd><NCM>19059090</NCM><CFOP>5403</CFOP><uCom>PC</uCom><qCom>30.0000</qCom><vUnCom>2.2496666667</vUnCom><vProd>67.49</vProd><cEANTrib>7897426020698</cEANTrib><uTrib>PC</uTrib><qTrib>30.0000</qTrib><vUnTrib>2.2496666667</vUnTrib><indTot>1</indTot><xPed>645000391</xPed><nItemPed>51</nItemPed></prod><imposto><ICMS><ICMS60><orig>0</orig><CST>60</CST><vBCSTRet>50.03</vBCSTRet><pST>18.0000</pST><vICMSSubstituto>0.00</vICMSSubstituto><vICMSSTRet>6.19</vICMSSTRet></ICMS60></ICMS><IPI><cEnq>999</cEnq><IPITrib><CST>99</CST><vBC>0.00</vBC><pIPI>0.0000</pIPI><vIPI>0.00</vIPI></IPITrib></IPI><PIS><PISAliq><CST>01</CST><vBC>67.48</vBC><pPIS>0.6500</pPIS><vPIS>0.44</vPIS></PISAliq></PIS><COFINS><COFINSAliq><CST>01</CST><vBC>67.48</vBC><pCOFINS>3.0000</pCOFINS><vCOFINS>2.02</vCOFINS></COFINSAliq></COFINS></imposto></det><det nItem="50"><prod><cProd>43210</cProd><cEAN>7897426020674</cEAN><xProd>PAO DE MEL SAGRA MORANGO COB. CHOCO 60G 30X60G QTD. 1.00 CX</xProd><NCM>19059090</NCM><CFOP>5403</CFOP><uCom>PC</uCom><qCom>30.0000</qCom><vUnCom>2.2496666667</vUnCom><vProd>67.49</vProd><cEANTrib>7897426020674</cEANTrib><uTrib>PC</uTrib><qTrib>30.0000</qTrib><vUnTrib>2.2496666667</vUnTrib><indTot>1</indTot><xPed>645000391</xPed><nItemPed>52</nItemPed></prod><imposto><ICMS><ICMS60><orig>0</orig><CST>60</CST><vBCSTRet>50.03</vBCSTRet><pST>18.0000</pST><vICMSSubstituto>0.00</vICMSSubstituto><vICMSSTRet>6.19</vICMSSTRet></ICMS60></ICMS><IPI><cEnq>999</cEnq><IPITrib><CST>99</CST><vBC>0.00</vBC><pIPI>0.0000</pIPI><vIPI>0.00</vIPI></IPITrib></IPI><PIS><PISAliq><CST>01</CST><vBC>67.48</vBC><pPIS>0.6500</pPIS><vPIS>0.44</vPIS></PISAliq></PIS><COFINS><COFINSAliq><CST>01</CST><vBC>67.48</vBC><pCOFINS>3.0000</pCOFINS><vCOFINS>2.02</vCOFINS></COFINSAliq></COFINS></imposto></det><det nItem="51"><prod><cProd>43225</cProd><cEAN>7897426020667</cEAN><xProd>PAO DE MEL SAGRA TRAD. COB.CHOCOLATE 60G 30X60G QTD. 1.00 CX</xProd><NCM>19059090</NCM><CFOP>5403</CFOP><uCom>PC</uCom><qCom>30.0000</qCom><vUnCom>2.2496666667</vUnCom><vProd>67.49</vProd><cEANTrib>7897426020667</cEANTrib><uTrib>PC</uTrib><qTrib>30.0000</qTrib><vUnTrib>2.2496666667</vUnTrib><indTot>1</indTot><xPed>645000391</xPed><nItemPed>53</nItemPed></prod><imposto><ICMS><ICMS60><orig>0</orig><CST>60</CST><vBCSTRet>50.03</vBCSTRet><pST>18.0000</pST><vICMSSubstituto>0.00</vICMSSubstituto><vICMSSTRet>6.19</vICMSSTRet></ICMS60></ICMS><IPI><cEnq>999</cEnq><IPITrib><CST>99</CST><vBC>0.00</vBC><pIPI>0.0000</pIPI><vIPI>0.00</vIPI></IPITrib></IPI><PIS><PISAliq><CST>01</CST><vBC>67.48</vBC><pPIS>0.6500</pPIS><vPIS>0.44</vPIS></PISAliq></PIS><COFINS><COFINSAliq><CST>01</CST><vBC>67.48</vBC><pCOFINS>3.0000</pCOFINS><vCOFINS>2.02</vCOFINS></COFINSAliq></COFINS></imposto></det><det nItem="52"><prod><cProd>834</cProd><cEAN>7896383050489</cEAN><xProd>PE DE MOLEQUE CROCANTE POTE 6X750G 6X750G QTD. 1.00 CX</xProd><NCM>17049090</NCM><CFOP>5403</CFOP><uCom>PT</uCom><qCom>6.0000</qCom><vUnCom>19.6833333333</vUnCom><vProd>118.10</vProd><cEANTrib>7896383050489</cEANTrib><uTrib>PT</uTrib><qTrib>6.0000</qTrib><vUnTrib>19.6833333333</vUnTrib><indTot>1</indTot><xPed>645000391</xPed><nItemPed>54</nItemPed></prod><imposto><ICMS><ICMS60><orig>0</orig><CST>60</CST><vBCSTRet>81.13</vBCSTRet><pST>18.0000</pST><vICMSSubstituto>0.00</vICMSSubstituto><vICMSSTRet>10.86</vICMSSTRet></ICMS60></ICMS><IPI><cEnq>999</cEnq><IPITrib><CST>99</CST><vBC>0.00</vBC><pIPI>0.0000</pIPI><vIPI>0.00</vIPI></IPITrib></IPI><PIS><PISAliq><CST>01</CST><vBC>118.10</vBC><pPIS>0.6500</pPIS><vPIS>0.77</vPIS></PISAliq></PIS><COFINS><COFINSAliq><CST>01</CST><vBC>118.10</vBC><pCOFINS>3.0000</pCOFINS><vCOFINS>3.54</vCOFINS></COFINSAliq></COFINS></imposto></det><det nItem="53"><prod><cProd>833</cProd><cEAN>7896383051424</cEAN><xProd>PINGO DE LEITE TRADICIONAL 12X500G 12X500G QTD. 1.00 CX</xProd><NCM>19019020</NCM><CEST>1702900</CEST><indEscala>S</indEscala><CFOP>5403</CFOP><uCom>PT</uCom><qCom>12.0000</qCom><vUnCom>18.5583333333</vUnCom><vProd>222.70</vProd><cEANTrib>7896383051424</cEANTrib><uTrib>PT</uTrib><qTrib>12.0000</qTrib><vUnTrib>18.5583333333</vUnTrib><indTot>1</indTot><xPed>645000391</xPed><nItemPed>55</nItemPed></prod><imposto><ICMS><ICMS60><orig>0</orig><CST>60</CST><vBCSTRet>135.29</vBCSTRet><pST>20.0000</pST><vICMSSubstituto>0.00</vICMSSubstituto><vICMSSTRet>19.78</vICMSSTRet></ICMS60></ICMS><IPI><cEnq>999</cEnq><IPITrib><CST>99</CST><vBC>0.00</vBC><pIPI>0.0000</pIPI><vIPI>0.00</vIPI></IPITrib></IPI><PIS><PISAliq><CST>01</CST><vBC>222.70</vBC><pPIS>0.6500</pPIS><vPIS>1.45</vPIS></PISAliq></PIS><COFINS><COFINSAliq><CST>01</CST><vBC>222.70</vBC><pCOFINS>3.0000</pCOFINS><vCOFINS>6.68</vCOFINS></COFINSAliq></COFINS></imposto></det><det nItem="54"><prod><cProd>5218</cProd><cEAN>7896306615313</cEAN><xProd>PIRULITO BLONG BLUE 12X672G 12X672G QTD. 1.00 CX</xProd><NCM>17049020</NCM><CEST>2804100</CEST><indEscala>S</indEscala><CFOP>5102</CFOP><uCom>PC</uCom><qCom>12.0000</qCom><vUnCom>13.5908333333</vUnCom><vProd>163.09</vProd><cEANTrib>7896306615313</cEANTrib><uTrib>PC</uTrib><qTrib>12.0000</qTrib><vUnTrib>13.5908333333</vUnTrib><indTot>1</indTot><xPed>645000391</xPed><nItemPed>56</nItemPed></prod><imposto><vTotTrib>32.62</vTotTrib><ICMS><ICMS00><orig>0</orig><CST>00</CST><modBC>3</modBC><vBC>163.09</vBC><pICMS>20.0000</pICMS><vICMS>32.62</vICMS></ICMS00></ICMS><IPI><cEnq>999</cEnq><IPITrib><CST>99</CST><vBC>0.00</vBC><pIPI>0.0000</pIPI><vIPI>0.00</vIPI></IPITrib></IPI><PIS><PISAliq><CST>01</CST><vBC>163.09</vBC><pPIS>0.6500</pPIS><vPIS>1.06</vPIS></PISAliq></PIS><COFINS><COFINSAliq><CST>01</CST><vBC>163.09</vBC><pCOFINS>3.0000</pCOFINS><vCOFINS>4.89</vCOFINS></COFINSAliq></COFINS></imposto></det><det nItem="55"><prod><cProd>984</cProd><cEAN>7896306610974</cEAN><xProd>PIRULITO BLONG MORANGO 12X672G 12X672G QTD. 1.00 CX</xProd><NCM>17049020</NCM><CEST>2804100</CEST><indEscala>S</indEscala><CFOP>5102</CFOP><uCom>PC</uCom><qCom>12.0000</qCom><vUnCom>13.5908333333</vUnCom><vProd>163.09</vProd><cEANTrib>7896306610974</cEANTrib><uTrib>PC</uTrib><qTrib>12.0000</qTrib><vUnTrib>13.5908333333</vUnTrib><indTot>1</indTot><xPed>645000391</xPed><nItemPed>57</nItemPed></prod><imposto><vTotTrib>32.62</vTotTrib><ICMS><ICMS00><orig>0</orig><CST>00</CST><modBC>3</modBC><vBC>163.09</vBC><pICMS>20.0000</pICMS><vICMS>32.62</vICMS></ICMS00></ICMS><IPI><cEnq>999</cEnq><IPITrib><CST>99</CST><vBC>0.00</vBC><pIPI>0.0000</pIPI><vIPI>0.00</vIPI></IPITrib></IPI><PIS><PISAliq><CST>01</CST><vBC>163.09</vBC><pPIS>0.6500</pPIS><vPIS>1.06</vPIS></PISAliq></PIS><COFINS><COFINSAliq><CST>01</CST><vBC>163.09</vBC><pCOFINS>3.0000</pCOFINS><vCOFINS>4.89</vCOFINS></COFINSAliq></COFINS></imposto></det><det nItem="56"><prod><cProd>48680</cProd><cEAN>07908228802853</cEAN><xProd>REGALIZ TUBES MORANGO 6X10X40G 400G QTD. 2.00 DP</xProd><NCM>17049020</NCM><CEST>2804100</CEST><indEscala>S</indEscala><CFOP>5102</CFOP><uCom>DP</uCom><qCom>2.0000</qCom><vUnCom>28.5400000000</vUnCom><vProd>57.08</vProd><cEANTrib>07908228802853</cEANTrib><uTrib>DP</uTrib><qTrib>2.0000</qTrib><vUnTrib>28.5400000000</vUnTrib><indTot>1</indTot><xPed>645000391</xPed><nItemPed>58</nItemPed></prod><imposto><vTotTrib>11.42</vTotTrib><ICMS><ICMS00><orig>0</orig><CST>00</CST><modBC>3</modBC><vBC>57.08</vBC><pICMS>20.0000</pICMS><vICMS>11.42</vICMS></ICMS00></ICMS><IPI><cEnq>999</cEnq><IPITrib><CST>99</CST><vBC>0.00</vBC><pIPI>0.0000</pIPI><vIPI>0.00</vIPI></IPITrib></IPI><PIS><PISAliq><CST>01</CST><vBC>57.08</vBC><pPIS>0.6500</pPIS><vPIS>0.37</vPIS></PISAliq></PIS><COFINS><COFINSAliq><CST>01</CST><vBC>57.08</vBC><pCOFINS>3.0000</pCOFINS><vCOFINS>1.71</vCOFINS></COFINSAliq></COFINS></imposto></det><det nItem="57"><prod><cProd>48681</cProd><cEAN>7908228802839</cEAN><xProd>REGALIZ TUBES MORANGO CIT 6X10X40G 400G QTD. 2.00 DP</xProd><NCM>17049020</NCM><CEST>2804100</CEST><indEscala>S</indEscala><CFOP>5102</CFOP><uCom>DP</uCom><qCom>2.0000</qCom><vUnCom>28.5400000000</vUnCom><vProd>57.08</vProd><cEANTrib>7908228802839</cEANTrib><uTrib>DP</uTrib><qTrib>2.0000</qTrib><vUnTrib>28.5400000000</vUnTrib><indTot>1</indTot><xPed>645000391</xPed><nItemPed>59</nItemPed></prod><imposto><vTotTrib>11.42</vTotTrib><ICMS><ICMS00><orig>0</orig><CST>00</CST><modBC>3</modBC><vBC>57.08</vBC><pICMS>20.0000</pICMS><vICMS>11.42</vICMS></ICMS00></ICMS><IPI><cEnq>999</cEnq><IPITrib><CST>99</CST><vBC>0.00</vBC><pIPI>0.0000</pIPI><vIPI>0.00</vIPI></IPITrib></IPI><PIS><PISAliq><CST>01</CST><vBC>57.08</vBC><pPIS>0.6500</pPIS><vPIS>0.37</vPIS></PISAliq></PIS><COFINS><COFINSAliq><CST>01</CST><vBC>57.08</vBC><pCOFINS>3.0000</pCOFINS><vCOFINS>1.71</vCOFINS></COFINSAliq></COFINS></imposto></det><det nItem="58"><prod><cProd>48682</cProd><cEAN>07908228802792</cEAN><xProd>REGALIZ TUBES TUTTI FRUTTI CI 6X10X40G 400G QTD. 2.00 DP</xProd><NCM>17049020</NCM><CEST>2804100</CEST><indEscala>S</indEscala><CFOP>5102</CFOP><uCom>DP</uCom><qCom>2.0000</qCom><vUnCom>28.5400000000</vUnCom><vProd>57.08</vProd><cEANTrib>07908228802792</cEANTrib><uTrib>DP</uTrib><qTrib>2.0000</qTrib><vUnTrib>28.5400000000</vUnTrib><indTot>1</indTot><xPed>645000391</xPed><nItemPed>60</nItemPed></prod><imposto><vTotTrib>11.42</vTotTrib><ICMS><ICMS00><orig>0</orig><CST>00</CST><modBC>3</modBC><vBC>57.08</vBC><pICMS>20.0000</pICMS><vICMS>11.42</vICMS></ICMS00></ICMS><IPI><cEnq>999</cEnq><IPITrib><CST>99</CST><vBC>0.00</vBC><pIPI>0.0000</pIPI><vIPI>0.00</vIPI></IPITrib></IPI><PIS><PISAliq><CST>01</CST><vBC>57.08</vBC><pPIS>0.6500</pPIS><vPIS>0.37</vPIS></PISAliq></PIS><COFINS><COFINSAliq><CST>01</CST><vBC>57.08</vBC><pCOFINS>3.0000</pCOFINS><vCOFINS>1.71</vCOFINS></COFINSAliq></COFINS></imposto></det><det nItem="59"><prod><cProd>50493</cProd><cEAN>7898950172099</cEAN><xProd>SEQUILHOS BAUNILHA PORTO ALEGRE 28X100G 28X100G QTD. 1.00 CX</xProd><NCM>19053100</NCM><CEST>1705400</CEST><indEscala>S</indEscala><CFOP>5403</CFOP><uCom>UN</uCom><qCom>28.0000</qCom><vUnCom>4.1239285714</vUnCom><vProd>115.47</vProd><cEANTrib>7898950172099</cEANTrib><uTrib>UN</uTrib><qTrib>28.0000</qTrib><vUnTrib>4.1239285714</vUnTrib><indTot>1</indTot><xPed>645000391</xPed><nItemPed>61</nItemPed></prod><imposto><ICMS><ICMS60><orig>1</orig><CST>60</CST><vBCSTRet>61.69</vBCSTRet><pST>18.0000</pST><vICMSSubstituto>0.00</vICMSSubstituto><vICMSSTRet>7.64</vICMSSTRet></ICMS60></ICMS><IPI><cEnq>999</cEnq><IPITrib><CST>99</CST><vBC>0.00</vBC><pIPI>0.0000</pIPI><vIPI>0.00</vIPI></IPITrib></IPI><PIS><PISAliq><CST>01</CST><vBC>115.47</vBC><pPIS>0.6500</pPIS><vPIS>0.75</vPIS></PISAliq></PIS><COFINS><COFINSAliq><CST>01</CST><vBC>115.47</vBC><pCOFINS>3.0000</pCOFINS><vCOFINS>3.46</vCOFINS></COFINSAliq></COFINS></imposto></det><det nItem="60"><prod><cProd>50494</cProd><cEAN>7898950172112</cEAN><xProd>SEQUILHOS LARANJA PORTO ALEGRE 28X100G 28X100G QTD. 1.00 CX</xProd><NCM>19053100</NCM><CEST>1705400</CEST><indEscala>S</indEscala><CFOP>5403</CFOP><uCom>UN</uCom><qCom>28.0000</qCom><vUnCom>4.1239285714</vUnCom><vProd>115.47</vProd><cEANTrib>7898950172112</cEANTrib><uTrib>UN</uTrib><qTrib>28.0000</qTrib><vUnTrib>4.1239285714</vUnTrib><indTot>1</indTot><xPed>645000391</xPed><nItemPed>62</nItemPed></prod><imposto><ICMS><ICMS60><orig>1</orig><CST>60</CST><vBCSTRet>61.69</vBCSTRet><pST>18.0000</pST><vICMSSubstituto>0.00</vICMSSubstituto><vICMSSTRet>7.64</vICMSSTRet></ICMS60></ICMS><IPI><cEnq>999</cEnq><IPITrib><CST>99</CST><vBC>0.00</vBC><pIPI>0.0000</pIPI><vIPI>0.00</vIPI></IPITrib></IPI><PIS><PISAliq><CST>01</CST><vBC>115.47</vBC><pPIS>0.6500</pPIS><vPIS>0.75</vPIS></PISAliq></PIS><COFINS><COFINSAliq><CST>01</CST><vBC>115.47</vBC><pCOFINS>3.0000</pCOFINS><vCOFINS>3.46</vCOFINS></COFINSAliq></COFINS></imposto></det><det nItem="61"><prod><cProd>14834</cProd><cEAN>7896383073532</cEAN><xProd>TUBITOS POTE 750G 6X50UNX15G 6X50UNX15G QTD. 4.00 CX</xProd><NCM>17049090</NCM><CFOP>5403</CFOP><uCom>PT</uCom><qCom>24.0000</qCom><vUnCom>16.2154166667</vUnCom><vProd>389.17</vProd><cEANTrib>7896383073532</cEANTrib><uTrib>PT</uTrib><qTrib>24.0000</qTrib><vUnTrib>16.2154166667</vUnTrib><indTot>1</indTot><xPed>645000391</xPed><nItemPed>63</nItemPed></prod><imposto><ICMS><ICMS60><orig>0</orig><CST>60</CST><vBCSTRet>280.51</vBCSTRet><pST>20.0000</pST><vICMSSubstituto>0.00</vICMSSubstituto><vICMSSTRet>43.14</vICMSSTRet></ICMS60></ICMS><IPI><cEnq>999</cEnq><IPITrib><CST>99</CST><vBC>0.00</vBC><pIPI>0.0000</pIPI><vIPI>0.00</vIPI></IPITrib></IPI><PIS><PISAliq><CST>01</CST><vBC>389.17</vBC><pPIS>0.6500</pPIS><vPIS>2.53</vPIS></PISAliq></PIS><COFINS><COFINSAliq><CST>01</CST><vBC>389.17</vBC><pCOFINS>3.0000</pCOFINS><vCOFINS>11.68</vCOFINS></COFINSAliq></COFINS></imposto></det><total><ICMSTot><vBC>6813.86</vBC><vICMS>1362.84</vICMS><vICMSDeson>0.00</vICMSDeson><vFCP>0.00</vFCP><vBCST>0.00</vBCST><vST>0.00</vST><vFCPST>0.00</vFCPST><vFCPSTRet>0.00</vFCPSTRet><vProd>15240.99</vProd><vFrete>0.00</vFrete><vSeg>0.00</vSeg><vDesc>0.00</vDesc><vII>0.00</vII><vIPI>0.00</vIPI><vIPIDevol>0.00</vIPIDevol><vPIS>99.05</vPIS><vCOFINS>457.13</vCOFINS><vOutro>0.00</vOutro><vNF>15240.99</vNF><vTotTrib>1362.84</vTotTrib></ICMSTot></total><transp><modFrete>3</modFrete><transporta><CNPJ>08214295000372</CNPJ><xNome>SUPER CANCUN COMERCIO DE PRODUTOS ALIMENTICIOS LTDA</xNome><IE>042297435</IE><xEnder>RUA CERINA SOUTO, 90 - PONTA NEGRA</xEnder><xMun>MANAUS</xMun><UF>AM</UF></transporta><veicTransp><placa>PHZ1800</placa><UF>AM</UF></veicTransp><vol><qVol>133</qVol><nVol>133</nVol><pesoL>833.556</pesoL><pesoB>888.763</pesoB></vol></transp><cobr><fat><nFat>180975</nFat><vOrig>15240.99</vOrig><vDesc>0</vDesc><vLiq>15240.99</vLiq></fat><dup><nDup>001</nDup><dVenc>2023-08-14</dVenc><vDup>2540.14</vDup></dup><dup><nDup>002</nDup><dVenc>2023-08-21</dVenc><vDup>2540.17</vDup></dup><dup><nDup>003</nDup><dVenc>2023-08-28</dVenc><vDup>2540.17</vDup></dup><dup><nDup>004</nDup><dVenc>2023-09-04</dVenc><vDup>2540.17</vDup></dup><dup><nDup>005</nDup><dVenc>2023-09-11</dVenc><vDup>2540.17</vDup></dup><dup><nDup>006</nDup><dVenc>2023-09-18</dVenc><vDup>2540.17</vDup></dup></cobr><pag><detPag><indPag>1</indPag><tPag>15</tPag><vPag>15240.99</vPag></detPag></pag><infIntermed><CNPJ>10766206000180</CNPJ><idCadIntTran>Maxima Sistemas de Informatica SA</idCadIntTran></infIntermed><infAdic><infAdFisco>//f/b VENCEDOR SAO RDO</infAdFisco><infCpl>f/b VENCEDOR SAO RDO//vencedor sai terca//NUM. TRANS.: 102277776//NR. PEDIDO: 645000391//NUMOS: 1573418//NUM. CARREG.: 127352//FANTASIA: SUPERMERCADO HELY//COD. COB.: 237//COD. CLIENTE.: 4059// //ALTERACAO DA ALIQUOTA MODAL DE ICMS CONF. LEI COMP 242/2022//MERCADORIAS SUJEITA AO REGIME DE ST CONF. LEI 6.108/2022//f/b VENCEDOR SAO RDO</infCpl></infAdic><infRespTec><CNPJ>07577599000501</CNPJ><xContato>TOTVS BRASILIA SOFTWARE - UNIDADE GOIANIA LTDA</xContato><email>resp_tecnico_dfe_winthor@totvs.com.br</email><fone>06232500200</fone></infRespTec></infNFe><Signature xmlns="http://www.w3.org/2000/09/xmldsig#"><SignedInfo><CanonicalizationMethod Algorithm="http://www.w3.org/TR/2001/REC-xml-c14n-20010315" /><SignatureMethod Algorithm="http://www.w3.org/2000/09/xmldsig#rsa-sha1" /><Reference URI="#NFe13230708214295000372550010001809751550392342"><Transforms><Transform Algorithm="http://www.w3.org/2000/09/xmldsig#enveloped-signature" /><Transform Algorithm="http://www.w3.org/TR/2001/REC-xml-c14n-20010315" /></Transforms><DigestMethod Algorithm="http://www.w3.org/2000/09/xmldsig#sha1" /><DigestValue>k4wHWNaHgmCw5sxfK49T0Y2gITY=</DigestValue></Reference></SignedInfo><SignatureValue>YdAuNYGqXsmMNMLw3CpGAww0+wcNFTV1Gw51GkypQ4zYZz87bkJEvseC/9f6BY88h4Ts4lk1yL7N
N9luSow0R5Y32Y9qT6tI4ovKADenxbSmutFwh68GIj254wra0GqSdiZanb8HdKDXjYwRCvSwMi9n
ZdAhnVixxgGfsA0sdhGkKsA/p/DtiVDCwNmxgToz/PxQzDHko6VRSag8f8pJpdsp46/DnwN/94mZ
4jKRPAPjqPntu/mkBRGyotSZJWZ51m/oHSUUL1jBwB0XFkmV/p5fNNoC0pk6EumZ6xX05W9rfSka
2J5MK2GvnCBcemzceATTZJlO9uzKYmk8kE9VcA==</SignatureValue><KeyInfo><X509Data><X509Certificate>MIIHVzCCBT+gAwIBAgIIehAjASVR+y4wDQYJKoZIhvcNAQELBQAwWTELMAkGA1UEBhMCQlIxEzAR
BgNVBAoTCklDUC1CcmFzaWwxFTATBgNVBAsTDEFDIFNPTFVUSSB2NTEeMBwGA1UEAxMVQUMgU09M
VVRJIE11bHRpcGxhIHY1MB4XDTIzMDIxNTEzMjAwMFoXDTI0MDIxNTEzMjAwMFowgfUxCzAJBgNV
BAYTAkJSMRMwEQYDVQQKEwpJQ1AtQnJhc2lsMQswCQYDVQQIEwJBTTEPMA0GA1UEBxMGTWFuYXVz
MR4wHAYDVQQLExVBQyBTT0xVVEkgTXVsdGlwbGEgdjUxFzAVBgNVBAsTDjM0MjEyNjE1MDAwMTAx
MRMwEQYDVQQLEwpQcmVzZW5jaWFsMRowGAYDVQQLExFDZXJ0aWZpY2FkbyBQSiBBMTFJMEcGA1UE
AxNAU1VQRVIgQ0FOQ1VOIENPTUVSQ0lPIERFIFBST0RVVE9TIEFMSU1FTlRJQ0lPUyBMVDowODIx
NDI5NTAwMDEwMDCCASIwDQYJKoZIhvcNAQEBBQADggEPADCCAQoCggEBAI6QGKITB90HDFRgtzw9
rt+2kU9vU3TJXuaQB01t/kLbqcpuyl1joID8UtntbRCnFWrn0bKEBGkd/aFIPipNdizO+K0Y/um0
w9oma8NxQBWQ/G9MWxJnac9v/z27Wmv2jybcSAkMKfnIP386tfEv8HY/re1eBPOLSsB2DiZEnXNr
TV5BMF6zJRgjdQ4YtqSipSj4Wz2iwSCXcC/Gn9lDuswavzHl/0ZtCPWAzie8yZ9LVAYhQporKkG1
2nZbtklT4Vq43JJf/Dw0gy84jbaoVIrHo42ixwUDr31QEEcl05dU2Bvr/aYuBHcLLeuojm/6j2Sa
EteB37nBdK+31ljb+cUCAwEAAaOCAoQwggKAMAkGA1UdEwQCMAAwHwYDVR0jBBgwFoAUxVLtJYAJ
35yCyJ9Hxt20XzHdubEwVAYIKwYBBQUHAQEESDBGMEQGCCsGAQUFBzAChjhodHRwOi8vY2NkLmFj
c29sdXRpLmNvbS5ici9sY3IvYWMtc29sdXRpLW11bHRpcGxhLXY1LnA3YjCBvwYDVR0RBIG3MIG0
gRlmaXNjYWxAc3VwZXJjYW5jdW4uY29tLmJyoCkGBWBMAQMCoCATHlJVWSBNQUNIQURPIFZBTEVO
VEUgQ0FWQUxDQU5URaAZBgVgTAEDA6AQEw4wODIxNDI5NTAwMDEwMKA4BgVgTAEDBKAvEy0yMzEx
MTk3ODYzNjI4MzUwMjYzMDAwMDAwMDAwMDAwMDAwMDAwMDAwMDAwMDCgFwYFYEwBAwegDhMMMDAw
MDAwMDAwMDAwMF0GA1UdIARWMFQwUgYGYEwBAgEmMEgwRgYIKwYBBQUHAgEWOmh0dHA6Ly9jY2Qu
YWNzb2x1dGkuY29tLmJyL2RvY3MvZHBjLWFjLXNvbHV0aS1tdWx0aXBsYS5wZGYwHQYDVR0lBBYw
FAYIKwYBBQUHAwIGCCsGAQUFBwMEMIGMBgNVHR8EgYQwgYEwPqA8oDqGOGh0dHA6Ly9jY2QuYWNz
b2x1dGkuY29tLmJyL2xjci9hYy1zb2x1dGktbXVsdGlwbGEtdjUuY3JsMD+gPaA7hjlodHRwOi8v
Y2NkMi5hY3NvbHV0aS5jb20uYnIvbGNyL2FjLXNvbHV0aS1tdWx0aXBsYS12NS5jcmwwHQYDVR0O
BBYEFFyvBZVnkoie10mnTGhc9zQBZgwJMA4GA1UdDwEB/wQEAwIF4DANBgkqhkiG9w0BAQsFAAOC
AgEAuHBuAO5g9/z9U7elaIXTfEefrdMzuAfZc6m+b5J1oAssuuc8ZLHxWv0J7z/OJttwAlFRRBp7
/QWi6UgGJQhqJWtsA4usTShqirDtvR+gr3+iFd6gxwxL4AfcA6zye11HMx6kHckQEP+wYzjZgiJH
p2mHHOJClCyhEgqgUyvhddm9kCtoVpsVjv6JTGheu+yvuiOVYJjy++ygeQ8btLowCVwQbBNTSsxc
9KKhqAoqrnBX+67d59prQ8XpnDyTkbtOND7CRkLTpTyZPkz2H6lYOjN9G76MD3zUgxIx3INIpt9G
cZq47N0aWZyyn/QlLMrn7XGQk9JA5ohjApn/rC58auBmrXhKRwhITn7zfaXla56taZPcRKUtMSSc
djy+LfEvVBDhrS1V+58eYCXi0OBN7CfFD+Ubul0qeegl3tuzY7eKovXlsbVWKIxBwYA5bj3dpvnm
ldA0m1s8YNNBuPPyAHbTUKZ7BlAHpmhO/w88hvCVxAlnZK/kvYTsVvS9qpQqHLBkgnv2sKtco1oj
3+PUbs4NJRRA1jef8i46Ltamkq2U4ULKIRGAso1h1JO14grTzKFxhm3q9w58OpTNJ5oikhXxfXBo
qzvyua8/Mwhkp0fLVHYzXs2tKf6CQIBxa3SpbkTQfByE7FmV0+SdxQlyso5nU4SI8GKN6Tv4e9ch
OMs=</X509Certificate></X509Data></KeyInfo></Signature></NFe><protNFe xmlns="http://www.portalfiscal.inf.br/nfe" versao="4.00"><infProt Id="ID113232481771120"><tpAmb>1</tpAmb><verAplic>AM4.00</verAplic><chNFe>13230708214295000372550010001809751550392342</chNFe><dhRecbto>2023-07-21T17:55:55-04:00</dhRecbto><nProt>113232481771120</nProt><digVal>k4wHWNaHgmCw5sxfK49T0Y2gITY=</digVal><cStat>100</cStat><xMotivo>Autorizado o uso da NF-e</xMotivo></infProt></protNFe></nfeProc>
